[{"id":0,"numSamples":2279,"probLeft":0.7275120666959193,"probRight":0.2724879333040807,"isCategorical":"False","feature":15,"split":0,"leftChild":{"id":1,"numSamples":1658,"probLeft":0.8455971049457177,"probRight":0.15440289505428226,"isCategorical":"False","feature":52,"split":0,"leftChild":{"id":2,"numSamples":1402,"probLeft":0.7111269614835949,"probRight":0.2888730385164051,"isCategorical":"False","feature":18,"split":1,"leftChild":{"id":3,"numSamples":997,"probLeft":0.9699097291875627,"probRight":0.03009027081243731,"isCategorical":"False","feature":6,"split":0,"leftChild":{"id":4,"numSamples":967,"probLeft":0.9958634953464323,"probRight":0.004136504653567736,"isCategorical":"False","feature":36,"split":3,"leftChild":{"id":5,"numSamples":963,"prediction":[0.05896529562982005,0.0035347043701799484]},"rightChild": {"id":6,"numSamples":4,"prediction":[0.026785714285714284,0.03571428571428571]}},"rightChild": {"id":7,"numSamples":30,"probLeft":0.6333333333333333,"probRight":0.36666666666666664,"isCategorical":"False","feature":49,"split":0,"leftChild":{"id":8,"numSamples":19,"prediction":[0.00646551724137931,0.05603448275862069]},"rightChild": {"id":9,"numSamples":11,"prediction":[0.046875,0.015625]}}},"rightChild": {"id":10,"numSamples":405,"probLeft":0.9111111111111111,"probRight":0.08888888888888889,"isCategorical":"False","feature":7,"split":0,"leftChild":{"id":11,"numSamples":369,"probLeft":0.948509485094851,"probRight":0.051490514905149054,"isCategorical":"False","feature":55,"split":56,"leftChild":{"id":12,"numSamples":350,"prediction":[0.04805996472663139,0.014440035273368606]},"rightChild": {"id":13,"numSamples":19,"prediction":[0.003787878787878788,0.058712121212121215]}},"rightChild": {"id":14,"numSamples":36,"probLeft":0.8888888888888888,"probRight":0.1111111111111111,"isCategorical":"False","feature":2,"split":0,"leftChild":{"id":15,"numSamples":32,"prediction":[0.010638297872340425,0.05186170212765957]},"rightChild": {"id":16,"numSamples":4,"prediction":[0.041666666666666664,0.020833333333333332]}}}},"rightChild": {"id":17,"numSamples":256,"probLeft":0.375,"probRight":0.625,"isCategorical":"False","feature":51,"split":0,"leftChild":{"id":18,"numSamples":96,"probLeft":0.8854166666666666,"probRight":0.11458333333333333,"isCategorical":"False","feature":26,"split":0,"leftChild":{"id":19,"numSamples":85,"probLeft":0.5764705882352941,"probRight":0.4235294117647059,"isCategorical":"False","feature":54,"split":3,"leftChild":{"id":20,"numSamples":49,"prediction":[0.034926470588235295,0.027573529411764705]},"rightChild": {"id":21,"numSamples":36,"prediction":[0.004098360655737705,0.0584016393442623]}},"rightChild": {"id":22,"numSamples":11,"prediction":[0.0625,0.0]}},"rightChild": {"id":23,"numSamples":160,"probLeft":0.9875,"probRight":0.0125,"isCategorical":"False","feature":41,"split":0,"leftChild":{"id":24,"numSamples":158,"probLeft":0.9683544303797469,"probRight":0.03164556962025317,"isCategorical":"False","feature":25,"split":0,"leftChild":{"id":25,"numSamples":153,"prediction":[0.00175,0.06075]},"rightChild": {"id":26,"numSamples":5,"prediction":[0.0625,0.0]}},"rightChild": {"id":27,"numSamples":2,"prediction":[0.0625,0.0]}}}},"rightChild": {"id":28,"numSamples":621,"probLeft":0.9597423510466989,"probRight":0.040257648953301126,"isCategorical":"False","feature":26,"split":0,"leftChild":{"id":29,"numSamples":596,"probLeft":0.10067114093959731,"probRight":0.8993288590604027,"isCategorical":"False","feature":55,"split":9,"leftChild":{"id":30,"numSamples":60,"probLeft":0.7833333333333333,"probRight":0.21666666666666667,"isCategorical":"False","feature":6,"split":0,"leftChild":{"id":31,"numSamples":47,"probLeft":0.8085106382978723,"probRight":0.19148936170212766,"isCategorical":"False","feature":41,"split":0,"leftChild":{"id":32,"numSamples":38,"prediction":[0.03125,0.03125]},"rightChild": {"id":33,"numSamples":9,"prediction":[0.0625,0.0]}},"rightChild": {"id":34,"numSamples":13,"prediction":[0.0,0.0625]}},"rightChild": {"id":35,"numSamples":536,"probLeft":0.4197761194029851,"probRight":0.5802238805970149,"isCategorical":"False","feature":52,"split":0,"leftChild":{"id":36,"numSamples":225,"probLeft":0.4666666666666667,"probRight":0.5333333333333333,"isCategorical":"False","feature":51,"split":0,"leftChild":{"id":37,"numSamples":105,"prediction":[0.030416666666666668,0.03208333333333333]},"rightChild": {"id":38,"numSamples":120,"prediction":[0.005935754189944134,0.05656424581005587]}},"rightChild": {"id":39,"numSamples":311,"probLeft":0.5562700964630225,"probRight":0.4437299035369775,"isCategorical":"False","feature":16,"split":0,"leftChild":{"id":40,"numSamples":173,"prediction":[0.00544425087108014,0.057055749128919864]},"rightChild": {"id":41,"numSamples":138,"prediction":[0.0,0.0625]}}}},"rightChild": {"id":42,"numSamples":25,"prediction":[0.0625,0.0]}}},{"id":0,"numSamples":2327,"probLeft":0.5694026643747314,"probRight":0.4305973356252686,"isCategorical":"False","feature":55,"split":18,"leftChild":{"id":1,"numSamples":1325,"probLeft":0.8875471698113208,"probRight":0.11245283018867924,"isCategorical":"False","feature":52,"split":0,"leftChild":{"id":2,"numSamples":1176,"probLeft":0.9464285714285714,"probRight":0.05357142857142857,"isCategorical":"False","feature":6,"split":0,"leftChild":{"id":3,"numSamples":1113,"probLeft":0.9829290206648698,"probRight":0.017070979335130278,"isCategorical":"False","feature":14,"split":0,"leftChild":{"id":4,"numSamples":1094,"probLeft":0.7714808043875686,"probRight":0.22851919561243145,"isCategorical":"False","feature":25,"split":0,"leftChild":{"id":5,"numSamples":844,"prediction":[0.05529580152671756,0.007204198473282443]},"rightChild": {"id":6,"numSamples":250,"prediction":[0.0625,0.0]}},"rightChild": {"id":7,"numSamples":19,"probLeft":0.8421052631578947,"probRight":0.15789473684210525,"isCategorical":"False","feature":52,"split":0,"leftChild":{"id":8,"numSamples":16,"prediction":[0.04296875,0.01953125]},"rightChild": {"id":9,"numSamples":3,"prediction":[0.0,0.0625]}}},"rightChild": {"id":10,"numSamples":63,"probLeft":0.9206349206349206,"probRight":0.07936507936507936,"isCategorical":"False","feature":26,"split":0,"leftChild":{"id":11,"numSamples":58,"probLeft":0.6379310344827587,"probRight":0.3620689655172414,"isCategorical":"False","feature":2,"split":0,"leftChild":{"id":12,"numSamples":37,"prediction":[0.01,0.0525]},"rightChild": {"id":13,"numSamples":21,"prediction":[0.0,0.0625]}},"rightChild": {"id":14,"numSamples":5,"prediction":[0.0625,0.0]}}},"rightChild": {"id":15,"numSamples":149,"probLeft":0.6174496644295302,"probRight":0.3825503355704698,"isCategorical":"False","feature":15,"split":0,"leftChild":{"id":16,"numSamples":92,"probLeft":0.6739130434782609,"probRight":0.32608695652173914,"isCategorical":"False","feature":52,"split":0,"leftChild":{"id":17,"numSamples":62,"probLeft":0.8064516129032258,"probRight":0.1935483870967742,"isCategorical":"False","feature":24,"split":0,"leftChild":{"id":18,"numSamples":50,"prediction":[0.02027027027027027,0.04222972972972973]},"rightChild": {"id":19,"numSamples":12,"prediction":[0.0625,0.0]}},"rightChild": {"id":20,"numSamples":30,"probLeft":0.9333333333333333,"probRight":0.06666666666666667,"isCategorical":"False","feature":11,"split":1,"leftChild":{"id":21,"numSamples":28,"prediction":[0.00390625,0.05859375]},"rightChild": {"id":22,"numSamples":2,"prediction":[0.0625,0.0]}}},"rightChild": {"id":23,"numSamples":57,"probLeft":0.5789473684210527,"probRight":0.42105263157894735,"isCategorical":"False","feature":16,"split":0,"leftChild":{"id":24,"numSamples":33,"probLeft":0.9696969696969697,"probRight":0.030303030303030304,"isCategorical":"False","feature":10,"split":1,"leftChild":{"id":25,"numSamples":32,"prediction":[0.001201923076923077,0.06129807692307692]},"rightChild": {"id":26,"numSamples":1,"prediction":[0.0625,0.0]}},"rightChild": {"id":27,"numSamples":24,"prediction":[0.0,0.0625]}}}},"rightChild": {"id":28,"numSamples":1002,"probLeft":0.7864271457085829,"probRight":0.21357285429141717,"isCategorical":"False","feature":24,"split":0,"leftChild":{"id":29,"numSamples":788,"probLeft":0.26903553299492383,"probRight":0.7309644670050761,"isCategorical":"False","feature":51,"split":0,"leftChild":{"id":30,"numSamples":212,"probLeft":0.8207547169811321,"probRight":0.1792452830188679,"isCategorical":"False","feature":15,"split":0,"leftChild":{"id":31,"numSamples":174,"probLeft":0.8333333333333334,"probRight":0.16666666666666666,"isCategorical":"False","feature":26,"split":0,"leftChild":{"id":32,"numSamples":145,"prediction":[0.03430232558139535,0.02819767441860465]},"rightChild": {"id":33,"numSamples":29,"prediction":[0.0625,0.0]}},"rightChild": {"id":34,"numSamples":38,"probLeft":0.6578947368421053,"probRight":0.34210526315789475,"isCategorical":"False","feature":44,"split":0,"leftChild":{"id":35,"numSamples":25,"prediction":[0.005813953488372093,0.056686046511627904]},"rightChild": {"id":36,"numSamples":13,"prediction":[0.039473684210526314,0.023026315789473683]}}},"rightChild": {"id":37,"numSamples":576,"probLeft":0.984375,"probRight":0.015625,"isCategorical":"False","feature":45,"split":0,"leftChild":{"id":38,"numSamples":567,"probLeft":0.9982363315696648,"probRight":0.001763668430335097,"isCategorical":"False","feature":1,"split":3,"leftChild":{"id":39,"numSamples":566,"prediction":[0.003271537622682661,0.05922846237731734]},"rightChild": {"id":40,"numSamples":1,"prediction":[0.0625,0.0]}},"rightChild": {"id":41,"numSamples":9,"probLeft":0.8888888888888888,"probRight":0.1111111111111111,"isCategorical":"False","feature":3,"split":0,"leftChild":{"id":42,"numSamples":8,"prediction":[0.0625,0.0]},"rightChild": {"id":43,"numSamples":1,"prediction":[0.0,0.0625]}}}},"rightChild": {"id":44,"numSamples":214,"probLeft":0.9719626168224299,"probRight":0.028037383177570093,"isCategorical":"False","feature":2,"split":1,"leftChild":{"id":45,"numSamples":208,"probLeft":0.9663461538461539,"probRight":0.03365384615384615,"isCategorical":"False","feature":15,"split":0,"leftChild":{"id":46,"numSamples":201,"probLeft":0.9950248756218906,"probRight":0.004975124378109453,"isCategorical":"False","feature":50,"split":0,"leftChild":{"id":47,"numSamples":200,"prediction":[0.06052839116719243,0.001971608832807571]},"rightChild": {"id":48,"numSamples":1,"prediction":[0.0,0.0625]}},"rightChild": {"id":49,"numSamples":7,"probLeft":0.14285714285714285,"probRight":0.8571428571428571,"isCategorical":"False","feature":9,"split":0,"leftChild":{"id":50,"numSamples":1,"prediction":[0.0625,0.0]},"rightChild": {"id":51,"numSamples":6,"prediction":[0.008928571428571428,0.05357142857142857]}}},"rightChild": {"id":52,"numSamples":6,"probLeft":0.8333333333333334,"probRight":0.16666666666666666,"isCategorical":"False","feature":34,"split":0,"leftChild":{"id":53,"numSamples":5,"prediction":[0.0,0.0625]},"rightChild": {"id":54,"numSamples":1,"prediction":[0.0625,0.0]}}}}},{"id":0,"numSamples":2346,"probLeft":0.5664961636828645,"probRight":0.43350383631713557,"isCategorical":"False","feature":51,"split":0,"leftChild":{"id":1,"numSamples":1329,"probLeft":0.44996237772761477,"probRight":0.5500376222723853,"isCategorical":"False","feature":55,"split":9,"leftChild":{"id":2,"numSamples":598,"probLeft":0.9230769230769231,"probRight":0.07692307692307693,"isCategorical":"False","feature":4,"split":0,"leftChild":{"id":3,"numSamples":552,"probLeft":0.9909420289855072,"probRight":0.009057971014492754,"isCategorical":"False","feature":10,"split":0,"leftChild":{"id":4,"numSamples":547,"probLeft":0.9963436928702011,"probRight":0.003656307129798903,"isCategorical":"False","feature":52,"split":0,"leftChild":{"id":5,"numSamples":545,"prediction":[0.06016355140186916,0.002336448598130841]},"rightChild": {"id":6,"numSamples":2,"prediction":[0.008928571428571428,0.05357142857142857]}},"rightChild": {"id":7,"numSamples":5,"probLeft":0.4,"probRight":0.6,"isCategorical":"False","feature":11,"split":0,"leftChild":{"id":8,"numSamples":2,"prediction":[0.0,0.0625]},"rightChild": {"id":9,"numSamples":3,"prediction":[0.0625,0.0]}}},"rightChild": {"id":10,"numSamples":46,"probLeft":0.9347826086956522,"probRight":0.06521739130434782,"isCategorical":"False","feature":10,"split":0,"leftChild":{"id":11,"numSamples":43,"probLeft":0.9534883720930233,"probRight":0.046511627906976744,"isCategorical":"False","feature":17,"split":1,"leftChild":{"id":12,"numSamples":41,"prediction":[0.06066176470588235,0.001838235294117647]},"rightChild": {"id":13,"numSamples":2,"prediction":[0.0,0.0625]}},"rightChild": {"id":14,"numSamples":3,"prediction":[0.0,0.0625]}}},"rightChild": {"id":15,"numSamples":731,"probLeft":0.8850889192886456,"probRight":0.11491108071135431,"isCategorical":"False","feature":6,"split":0,"leftChild":{"id":16,"numSamples":647,"probLeft":0.9629057187017002,"probRight":0.03709428129829984,"isCategorical":"False","feature":4,"split":1,"leftChild":{"id":17,"numSamples":623,"probLeft":0.4622792937399679,"probRight":0.5377207062600321,"isCategorical":"False","feature":24,"split":0,"leftChild":{"id":18,"numSamples":288,"prediction":[0.04562236286919831,0.016877637130801686]},"rightChild": {"id":19,"numSamples":335,"prediction":[0.06190589353612167,0.000594106463878327]}},"rightChild": {"id":20,"numSamples":24,"probLeft":0.875,"probRight":0.125,"isCategorical":"False","feature":29,"split":0,"leftChild":{"id":21,"numSamples":21,"prediction":[0.020833333333333332,0.041666666666666664]},"rightChild": {"id":22,"numSamples":3,"prediction":[0.0625,0.0]}}},"rightChild": {"id":23,"numSamples":84,"probLeft":0.9047619047619048,"probRight":0.09523809523809523,"isCategorical":"False","feature":34,"split":0,"leftChild":{"id":24,"numSamples":76,"probLeft":0.881578947368421,"probRight":0.11842105263157894,"isCategorical":"False","feature":48,"split":0,"leftChild":{"id":25,"numSamples":67,"prediction":[0.003472222222222222,0.059027777777777776]},"rightChild": {"id":26,"numSamples":9,"prediction":[0.03125,0.03125]}},"rightChild": {"id":27,"numSamples":8,"prediction":[0.0625,0.0]}}}},"rightChild": {"id":28,"numSamples":1017,"probLeft":0.9469026548672567,"probRight":0.05309734513274336,"isCategorical":"False","feature":26,"split":0,"leftChild":{"id":29,"numSamples":963,"probLeft":0.5129802699896158,"probRight":0.48701973001038423,"isCategorical":"False","feature":15,"split":0,"leftChild":{"id":30,"numSamples":494,"probLeft":0.43724696356275305,"probRight":0.562753036437247,"isCategorical":"False","feature":20,"split":0,"leftChild":{"id":31,"numSamples":216,"probLeft":0.875,"probRight":0.125,"isCategorical":"False","feature":52,"split":0,"leftChild":{"id":32,"numSamples":189,"prediction":[0.047098214285714285,0.015401785714285715]},"rightChild": {"id":33,"numSamples":27,"prediction":[0.00744047619047619,0.05505952380952381]}},"rightChild": {"id":34,"numSamples":278,"probLeft":0.460431654676259,"probRight":0.539568345323741,"isCategorical":"False","feature":4,"split":0,"leftChild":{"id":35,"numSamples":128,"prediction":[0.022135416666666668,0.040364583333333336]},"rightChild": {"id":36,"numSamples":150,"prediction":[0.0022123893805309734,0.06028761061946902]}}},"rightChild": {"id":37,"numSamples":469,"probLeft":0.5565031982942431,"probRight":0.44349680170575695,"isCategorical":"False","feature":23,"split":0,"leftChild":{"id":38,"numSamples":261,"probLeft":0.4674329501915709,"probRight":0.5325670498084292,"isCategorical":"False","feature":51,"split":0,"leftChild":{"id":39,"numSamples":122,"prediction":[0.015542328042328041,0.046957671957671955]},"rightChild": {"id":40,"numSamples":139,"prediction":[0.001829268292682927,0.06067073170731707]}},"rightChild": {"id":41,"numSamples":208,"prediction":[0.0,0.0625]}}},"rightChild": {"id":42,"numSamples":54,"probLeft":0.25925925925925924,"probRight":0.7407407407407407,"isCategorical":"False","feature":49,"split":0,"leftChild":{"id":43,"numSamples":14,"probLeft":0.8571428571428571,"probRight":0.14285714285714285,"isCategorical":"False","feature":4,"split":0,"leftChild":{"id":44,"numSamples":12,"probLeft":0.6666666666666666,"probRight":0.3333333333333333,"isCategorical":"False","feature":51,"split":0,"leftChild":{"id":45,"numSamples":8,"prediction":[0.0625,0.0]},"rightChild": {"id":46,"numSamples":4,"prediction":[0.0546875,0.0078125]}},"rightChild": {"id":47,"numSamples":2,"prediction":[0.0625,0.0]}},"rightChild": {"id":48,"numSamples":40,"prediction":[0.0625,0.0]}}}},{"id":0,"numSamples":2325,"probLeft":0.5483870967741935,"probRight":0.45161290322580644,"isCategorical":"False","feature":20,"split":0,"leftChild":{"id":1,"numSamples":1275,"probLeft":0.6690196078431373,"probRight":0.33098039215686276,"isCategorical":"False","feature":24,"split":0,"leftChild":{"id":2,"numSamples":853,"probLeft":0.9050410316529894,"probRight":0.09495896834701055,"isCategorical":"False","feature":11,"split":1,"leftChild":{"id":3,"numSamples":772,"probLeft":0.9313471502590673,"probRight":0.06865284974093264,"isCategorical":"False","feature":22,"split":0,"leftChild":{"id":4,"numSamples":719,"probLeft":0.9290681502086231,"probRight":0.07093184979137691,"isCategorical":"False","feature":52,"split":0,"leftChild":{"id":5,"numSamples":668,"prediction":[0.050971441947565546,0.011528558052434457]},"rightChild": {"id":6,"numSamples":51,"prediction":[0.014285714285714285,0.048214285714285716]}},"rightChild": {"id":7,"numSamples":53,"probLeft":0.05660377358490566,"probRight":0.9433962264150944,"isCategorical":"False","feature":55,"split":6,"leftChild":{"id":8,"numSamples":3,"prediction":[0.0625,0.0]},"rightChild": {"id":9,"numSamples":50,"prediction":[0.004629629629629629,0.05787037037037037]}}},"rightChild": {"id":10,"numSamples":81,"probLeft":0.7901234567901234,"probRight":0.20987654320987653,"isCategorical":"False","feature":18,"split":2,"leftChild":{"id":11,"numSamples":64,"probLeft":0.984375,"probRight":0.015625,"isCategorical":"False","feature":54,"split":19,"leftChild":{"id":12,"numSamples":63,"prediction":[0.0625,0.0]},"rightChild": {"id":13,"numSamples":1,"prediction":[0.0,0.0625]}},"rightChild": {"id":14,"numSamples":17,"probLeft":0.8823529411764706,"probRight":0.11764705882352941,"isCategorical":"False","feature":42,"split":0,"leftChild":{"id":15,"numSamples":15,"prediction":[0.05048076923076923,0.01201923076923077]},"rightChild": {"id":16,"numSamples":2,"prediction":[0.0625,0.0]}}}},"rightChild": {"id":17,"numSamples":422,"probLeft":0.990521327014218,"probRight":0.009478672985781991,"isCategorical":"False","feature":15,"split":0,"leftChild":{"id":18,"numSamples":418,"probLeft":0.08851674641148326,"probRight":0.9114832535885168,"isCategorical":"False","feature":24,"split":0,"leftChild":{"id":19,"numSamples":37,"probLeft":0.918918918918919,"probRight":0.08108108108108109,"isCategorical":"False","feature":51,"split":0,"leftChild":{"id":20,"numSamples":34,"prediction":[0.0625,0.0]},"rightChild": {"id":21,"numSamples":3,"prediction":[0.0,0.0625]}},"rightChild": {"id":22,"numSamples":381,"probLeft":0.9973753280839895,"probRight":0.0026246719160104987,"isCategorical":"False","feature":56,"split":2294,"leftChild":{"id":23,"numSamples":380,"prediction":[0.06185121107266436,0.0006487889273356401]},"rightChild": {"id":24,"numSamples":1,"prediction":[0.0,0.0625]}}},"rightChild": {"id":25,"numSamples":4,"probLeft":0.5,"probRight":0.5,"isCategorical":"False","feature":30,"split":0,"leftChild":{"id":26,"numSamples":2,"prediction":[0.0,0.0625]},"rightChild": {"id":27,"numSamples":2,"prediction":[0.0625,0.0]}}}},"rightChild": {"id":28,"numSamples":1050,"probLeft":0.9314285714285714,"probRight":0.06857142857142857,"isCategorical":"False","feature":29,"split":0,"leftChild":{"id":29,"numSamples":978,"probLeft":0.9243353783231084,"probRight":0.07566462167689161,"isCategorical":"False","feature":24,"split":0,"leftChild":{"id":30,"numSamples":904,"probLeft":0.7234513274336283,"probRight":0.27654867256637167,"isCategorical":"False","feature":53,"split":0,"leftChild":{"id":31,"numSamples":654,"probLeft":0.4602446483180428,"probRight":0.5397553516819572,"isCategorical":"False","feature":4,"split":0,"leftChild":{"id":32,"numSamples":301,"prediction":[0.031914893617021274,0.030585106382978722]},"rightChild": {"id":33,"numSamples":353,"prediction":[0.006590909090909091,0.05590909090909091]}},"rightChild": {"id":34,"numSamples":250,"probLeft":0.452,"probRight":0.548,"isCategorical":"False","feature":10,"split":0,"leftChild":{"id":35,"numSamples":113,"prediction":[0.007251381215469613,0.055248618784530384]},"rightChild": {"id":36,"numSamples":137,"prediction":[0.0008259911894273128,0.06167400881057269]}}},"rightChild": {"id":37,"numSamples":74,"probLeft":0.9594594594594594,"probRight":0.04054054054054054,"isCategorical":"False","feature":55,"split":744,"leftChild":{"id":38,"numSamples":71,"probLeft":0.8028169014084507,"probRight":0.19718309859154928,"isCategorical":"False","feature":4,"split":0,"leftChild":{"id":39,"numSamples":57,"prediction":[0.060032894736842105,0.0024671052631578946]},"rightChild": {"id":40,"numSamples":14,"prediction":[0.036458333333333336,0.026041666666666668]}},"rightChild": {"id":41,"numSamples":3,"prediction":[0.0,0.0625]}}},"rightChild": {"id":42,"numSamples":72,"probLeft":0.027777777777777776,"probRight":0.9722222222222222,"isCategorical":"False","feature":24,"split":0,"leftChild":{"id":43,"numSamples":2,"probLeft":0.5,"probRight":0.5,"isCategorical":"False","feature":39,"split":0,"leftChild":{"id":44,"numSamples":1,"prediction":[0.0625,0.0]},"rightChild": {"id":45,"numSamples":1,"prediction":[0.0,0.0625]}},"rightChild": {"id":46,"numSamples":70,"prediction":[0.0625,0.0]}}}},{"id":0,"numSamples":2354,"probLeft":0.8113848768054376,"probRight":0.18861512319456245,"isCategorical":"False","feature":7,"split":0,"leftChild":{"id":1,"numSamples":1910,"probLeft":0.7282722513089005,"probRight":0.2717277486910995,"isCategorical":"False","feature":4,"split":0,"leftChild":{"id":2,"numSamples":1391,"probLeft":0.7426312005751258,"probRight":0.2573687994248742,"isCategorical":"False","feature":51,"split":0,"leftChild":{"id":3,"numSamples":1033,"probLeft":0.9002904162633107,"probRight":0.09970958373668926,"isCategorical":"False","feature":20,"split":1,"leftChild":{"id":4,"numSamples":930,"probLeft":0.9989247311827957,"probRight":0.001075268817204301,"isCategorical":"False","feature":19,"split":2,"leftChild":{"id":5,"numSamples":929,"prediction":[0.05769566736547869,0.004804332634521314]},"rightChild": {"id":6,"numSamples":1,"prediction":[0.0,0.0625]}},"rightChild": {"id":7,"numSamples":103,"probLeft":0.49514563106796117,"probRight":0.5048543689320388,"isCategorical":"False","feature":55,"split":10,"leftChild":{"id":8,"numSamples":51,"prediction":[0.06097560975609756,0.001524390243902439]},"rightChild": {"id":9,"numSamples":52,"prediction":[0.0379746835443038,0.0245253164556962]}}},"rightChild": {"id":10,"numSamples":358,"probLeft":0.5279329608938548,"probRight":0.4720670391061452,"isCategorical":"False","feature":56,"split":68,"leftChild":{"id":11,"numSamples":189,"probLeft":0.9417989417989417,"probRight":0.0582010582010582,"isCategorical":"False","feature":2,"split":1,"leftChild":{"id":12,"numSamples":178,"prediction":[0.043498168498168496,0.0190018315018315]},"rightChild": {"id":13,"numSamples":11,"prediction":[0.019736842105263157,0.04276315789473684]}},"rightChild": {"id":14,"numSamples":169,"probLeft":0.9112426035502958,"probRight":0.08875739644970414,"isCategorical":"False","feature":38,"split":0,"leftChild":{"id":15,"numSamples":154,"prediction":[0.011387711864406779,0.05111228813559322]},"rightChild": {"id":16,"numSamples":15,"prediction":[0.05965909090909091,0.002840909090909091]}}}},"rightChild": {"id":17,"numSamples":519,"probLeft":0.630057803468208,"probRight":0.3699421965317919,"isCategorical":"False","feature":55,"split":45,"leftChild":{"id":18,"numSamples":327,"probLeft":0.6850152905198776,"probRight":0.3149847094801223,"isCategorical":"False","feature":15,"split":0,"leftChild":{"id":19,"numSamples":224,"probLeft":0.8080357142857143,"probRight":0.19196428571428573,"isCategorical":"False","feature":18,"split":2,"leftChild":{"id":20,"numSamples":181,"prediction":[0.053036971830985914,0.009463028169014084]},"rightChild": {"id":21,"numSamples":43,"prediction":[0.022388059701492536,0.04011194029850746]}},"rightChild": {"id":22,"numSamples":103,"probLeft":0.9223300970873787,"probRight":0.07766990291262135,"isCategorical":"False","feature":25,"split":0,"leftChild":{"id":23,"numSamples":95,"prediction":[0.004934210526315789,0.05756578947368421]},"rightChild": {"id":24,"numSamples":8,"prediction":[0.04375,0.01875]}}},"rightChild": {"id":25,"numSamples":192,"probLeft":0.953125,"probRight":0.046875,"isCategorical":"False","feature":41,"split":0,"leftChild":{"id":26,"numSamples":183,"probLeft":0.9781420765027322,"probRight":0.02185792349726776,"isCategorical":"False","feature":43,"split":0,"leftChild":{"id":27,"numSamples":179,"prediction":[0.002840909090909091,0.05965909090909091]},"rightChild": {"id":28,"numSamples":4,"prediction":[0.05,0.0125]}},"rightChild": {"id":29,"numSamples":9,"probLeft":0.8888888888888888,"probRight":0.1111111111111111,"isCategorical":"False","feature":49,"split":0,"leftChild":{"id":30,"numSamples":8,"prediction":[0.0625,0.0]},"rightChild": {"id":31,"numSamples":1,"prediction":[0.0,0.0625]}}}}},"rightChild": {"id":32,"numSamples":444,"probLeft":0.25225225225225223,"probRight":0.7477477477477478,"isCategorical":"False","feature":18,"split":0,"leftChild":{"id":33,"numSamples":112,"probLeft":0.9196428571428571,"probRight":0.08035714285714286,"isCategorical":"False","feature":55,"split":107,"leftChild":{"id":34,"numSamples":103,"probLeft":0.20388349514563106,"probRight":0.7961165048543689,"isCategorical":"False","feature":56,"split":83,"leftChild":{"id":35,"numSamples":21,"probLeft":0.8095238095238095,"probRight":0.19047619047619047,"isCategorical":"False","feature":25,"split":0,"leftChild":{"id":36,"numSamples":17,"prediction":[0.01,0.0525]},"rightChild": {"id":37,"numSamples":4,"prediction":[0.0625,0.0]}},"rightChild": {"id":38,"numSamples":82,"probLeft":0.9512195121951219,"probRight":0.04878048780487805,"isCategorical":"False","feature":51,"split":0,"leftChild":{"id":39,"numSamples":78,"prediction":[0.05530973451327434,0.007190265486725664]},"rightChild": {"id":40,"numSamples":4,"prediction":[0.0,0.0625]}}},"rightChild": {"id":41,"numSamples":9,"prediction":[0.0,0.0625]}},"rightChild": {"id":42,"numSamples":332,"probLeft":0.9698795180722891,"probRight":0.030120481927710843,"isCategorical":"False","feature":30,"split":0,"leftChild":{"id":43,"numSamples":322,"probLeft":0.027950310559006212,"probRight":0.9720496894409938,"isCategorical":"False","feature":54,"split":1,"leftChild":{"id":44,"numSamples":9,"probLeft":0.6666666666666666,"probRight":0.3333333333333333,"isCategorical":"False","feature":20,"split":2,"leftChild":{"id":45,"numSamples":6,"prediction":[0.044642857142857144,0.017857142857142856]},"rightChild": {"id":46,"numSamples":3,"prediction":[0.0,0.0625]}},"rightChild": {"id":47,"numSamples":313,"probLeft":0.536741214057508,"probRight":0.46325878594249204,"isCategorical":"False","feature":12,"split":0,"leftChild":{"id":48,"numSamples":168,"prediction":[0.004134241245136187,0.058365758754863814]},"rightChild": {"id":49,"numSamples":145,"prediction":[0.00025201612903225806,0.06224798387096774]}}},"rightChild": {"id":50,"numSamples":10,"prediction":[0.0625,0.0]}}}},{"id":0,"numSamples":2336,"probLeft":0.5732020547945206,"probRight":0.4267979452054795,"isCategorical":"False","feature":55,"split":18,"leftChild":{"id":1,"numSamples":1339,"probLeft":0.9163554891710232,"probRight":0.08364451082897685,"isCategorical":"False","feature":7,"split":0,"leftChild":{"id":2,"numSamples":1227,"probLeft":0.9698451507742462,"probRight":0.03015484922575387,"isCategorical":"False","feature":23,"split":0,"leftChild":{"id":3,"numSamples":1190,"probLeft":0.9436974789915966,"probRight":0.05630252100840336,"isCategorical":"False","feature":6,"split":0,"leftChild":{"id":4,"numSamples":1123,"probLeft":0.8922528940338379,"probRight":0.10774710596616206,"isCategorical":"False","feature":51,"split":0,"leftChild":{"id":5,"numSamples":1002,"prediction":[0.057679844458846406,0.004820155541153597]},"rightChild": {"id":6,"numSamples":121,"prediction":[0.034242021276595744,0.028257978723404256]}},"rightChild": {"id":7,"numSamples":67,"probLeft":0.9552238805970149,"probRight":0.04477611940298507,"isCategorical":"False","feature":36,"split":0,"leftChild":{"id":8,"numSamples":64,"prediction":[0.003947368421052632,0.05855263157894737]},"rightChild": {"id":9,"numSamples":3,"prediction":[0.05,0.0125]}}},"rightChild": {"id":10,"numSamples":37,"probLeft":0.8918918918918919,"probRight":0.10810810810810811,"isCategorical":"False","feature":53,"split":0,"leftChild":{"id":11,"numSamples":33,"probLeft":0.9393939393939394,"probRight":0.06060606060606061,"isCategorical":"False","feature":44,"split":0,"leftChild":{"id":12,"numSamples":31,"prediction":[0.009510869565217392,0.05298913043478261]},"rightChild": {"id":13,"numSamples":2,"prediction":[0.0625,0.0]}},"rightChild": {"id":14,"numSamples":4,"prediction":[0.0625,0.0]}}},"rightChild": {"id":15,"numSamples":112,"probLeft":0.3125,"probRight":0.6875,"isCategorical":"False","feature":20,"split":0,"leftChild":{"id":16,"numSamples":35,"probLeft":0.34285714285714286,"probRight":0.6571428571428571,"isCategorical":"False","feature":55,"split":9,"leftChild":{"id":17,"numSamples":12,"prediction":[0.0625,0.0]},"rightChild": {"id":18,"numSamples":23,"probLeft":0.13043478260869565,"probRight":0.8695652173913043,"isCategorical":"False","feature":56,"split":59,"leftChild":{"id":19,"numSamples":3,"prediction":[0.0125,0.05]},"rightChild": {"id":20,"numSamples":20,"prediction":[0.058333333333333334,0.004166666666666667]}}},"rightChild": {"id":21,"numSamples":77,"probLeft":0.961038961038961,"probRight":0.03896103896103896,"isCategorical":"False","feature":45,"split":0,"leftChild":{"id":22,"numSamples":74,"probLeft":0.972972972972973,"probRight":0.02702702702702703,"isCategorical":"False","feature":25,"split":0,"leftChild":{"id":23,"numSamples":72,"prediction":[0.0026483050847457626,0.05985169491525424]},"rightChild": {"id":24,"numSamples":2,"prediction":[0.0625,0.0]}},"rightChild": {"id":25,"numSamples":3,"prediction":[0.0625,0.0]}}}},"rightChild": {"id":26,"numSamples":997,"probLeft":0.7853560682046138,"probRight":0.21464393179538616,"isCategorical":"False","feature":24,"split":0,"leftChild":{"id":27,"numSamples":783,"probLeft":0.44189016602809705,"probRight":0.558109833971903,"isCategorical":"False","feature":52,"split":0,"leftChild":{"id":28,"numSamples":346,"probLeft":0.6820809248554913,"probRight":0.3179190751445087,"isCategorical":"False","feature":15,"split":0,"leftChild":{"id":29,"numSamples":236,"probLeft":0.8940677966101694,"probRight":0.1059322033898305,"isCategorical":"False","feature":23,"split":0,"leftChild":{"id":30,"numSamples":211,"prediction":[0.03412576687116564,0.028374233128834355]},"rightChild": {"id":31,"numSamples":25,"prediction":[0.0046875,0.0578125]}},"rightChild": {"id":32,"numSamples":110,"probLeft":0.990909090909091,"probRight":0.00909090909090909,"isCategorical":"False","feature":12,"split":0,"leftChild":{"id":33,"numSamples":109,"prediction":[0.008167613636363636,0.05433238636363636]},"rightChild": {"id":34,"numSamples":1,"prediction":[0.0625,0.0]}}},"rightChild": {"id":35,"numSamples":437,"probLeft":0.9931350114416476,"probRight":0.006864988558352402,"isCategorical":"False","feature":26,"split":0,"leftChild":{"id":36,"numSamples":434,"probLeft":0.9953917050691244,"probRight":0.004608294930875576,"isCategorical":"False","feature":40,"split":0,"leftChild":{"id":37,"numSamples":432,"prediction":[0.00221004243281471,0.06028995756718529]},"rightChild": {"id":38,"numSamples":2,"prediction":[0.0625,0.0]}},"rightChild": {"id":39,"numSamples":3,"probLeft":0.6666666666666666,"probRight":0.3333333333333333,"isCategorical":"False","feature":5,"split":0,"leftChild":{"id":40,"numSamples":2,"prediction":[0.0625,0.0]},"rightChild": {"id":41,"numSamples":1,"prediction":[0.0,0.0625]}}}},"rightChild": {"id":42,"numSamples":214,"probLeft":0.9485981308411215,"probRight":0.0514018691588785,"isCategorical":"False","feature":51,"split":0,"leftChild":{"id":43,"numSamples":203,"probLeft":0.8423645320197044,"probRight":0.15763546798029557,"isCategorical":"False","feature":22,"split":0,"leftChild":{"id":44,"numSamples":171,"probLeft":0.9941520467836257,"probRight":0.005847953216374269,"isCategorical":"False","feature":30,"split":1,"leftChild":{"id":45,"numSamples":170,"prediction":[0.061810661764705885,0.0006893382352941177]},"rightChild": {"id":46,"numSamples":1,"prediction":[0.0,0.0625]}},"rightChild": {"id":47,"numSamples":32,"probLeft":0.84375,"probRight":0.15625,"isCategorical":"False","feature":48,"split":0,"leftChild":{"id":48,"numSamples":27,"prediction":[0.05592105263157895,0.006578947368421052]},"rightChild": {"id":49,"numSamples":5,"prediction":[0.017857142857142856,0.044642857142857144]}}},"rightChild": {"id":50,"numSamples":11,"prediction":[0.0,0.0625]}}}},{"id":0,"numSamples":2360,"probLeft":0.8694915254237288,"probRight":0.13050847457627118,"isCategorical":"False","feature":22,"split":0,"leftChild":{"id":1,"numSamples":2052,"probLeft":0.8328460038986355,"probRight":0.16715399610136453,"isCategorical":"False","feature":52,"split":0,"leftChild":{"id":2,"numSamples":1709,"probLeft":0.85020479812756,"probRight":0.14979520187244003,"isCategorical":"False","feature":15,"split":0,"leftChild":{"id":3,"numSamples":1453,"probLeft":0.7322780454232622,"probRight":0.2677219545767378,"isCategorical":"False","feature":18,"split":2,"leftChild":{"id":4,"numSamples":1064,"probLeft":0.9473684210526315,"probRight":0.05263157894736842,"isCategorical":"False","feature":5,"split":0,"leftChild":{"id":5,"numSamples":1008,"prediction":[0.05889803673210893,0.00360196326789107]},"rightChild": {"id":6,"numSamples":56,"prediction":[0.04454022988505747,0.017959770114942528]}},"rightChild": {"id":7,"numSamples":389,"probLeft":0.897172236503856,"probRight":0.10282776349614396,"isCategorical":"False","feature":4,"split":1,"leftChild":{"id":8,"numSamples":349,"prediction":[0.04863861386138614,0.013861386138613862]},"rightChild": {"id":9,"numSamples":40,"prediction":[0.01585820895522388,0.04664179104477612]}}},"rightChild": {"id":10,"numSamples":256,"probLeft":0.90625,"probRight":0.09375,"isCategorical":"False","feature":25,"split":0,"leftChild":{"id":11,"numSamples":232,"probLeft":0.9439655172413793,"probRight":0.05603448275862069,"isCategorical":"False","feature":41,"split":0,"leftChild":{"id":12,"numSamples":219,"prediction":[0.016001506024096387,0.04649849397590362]},"rightChild": {"id":13,"numSamples":13,"prediction":[0.06018518518518518,0.0023148148148148147]}},"rightChild": {"id":14,"numSamples":24,"probLeft":0.875,"probRight":0.125,"isCategorical":"False","feature":6,"split":0,"leftChild":{"id":15,"numSamples":21,"prediction":[0.058823529411764705,0.003676470588235294]},"rightChild": {"id":16,"numSamples":3,"prediction":[0.020833333333333332,0.041666666666666664]}}}},"rightChild": {"id":17,"numSamples":343,"probLeft":0.8892128279883382,"probRight":0.11078717201166181,"isCategorical":"False","feature":24,"split":0,"leftChild":{"id":18,"numSamples":305,"probLeft":0.9934426229508196,"probRight":0.006557377049180328,"isCategorical":"False","feature":33,"split":0,"leftChild":{"id":19,"numSamples":303,"probLeft":0.9834983498349835,"probRight":0.0165016501650165,"isCategorical":"False","feature":45,"split":0,"leftChild":{"id":20,"numSamples":298,"prediction":[0.003598081023454158,0.05890191897654584]},"rightChild": {"id":21,"numSamples":5,"prediction":[0.05357142857142857,0.008928571428571428]}},"rightChild": {"id":22,"numSamples":2,"probLeft":0.5,"probRight":0.5,"isCategorical":"False","feature":1,"split":0,"leftChild":{"id":23,"numSamples":1,"prediction":[0.0625,0.0]},"rightChild": {"id":24,"numSamples":1,"prediction":[0.0,0.0625]}}},"rightChild": {"id":25,"numSamples":38,"probLeft":0.9473684210526315,"probRight":0.05263157894736842,"isCategorical":"False","feature":6,"split":0,"leftChild":{"id":26,"numSamples":36,"prediction":[0.0625,0.0]},"rightChild": {"id":27,"numSamples":2,"prediction":[0.0,0.0625]}}}},"rightChild": {"id":28,"numSamples":308,"probLeft":0.8896103896103896,"probRight":0.11038961038961038,"isCategorical":"False","feature":36,"split":0,"leftChild":{"id":29,"numSamples":274,"probLeft":0.043795620437956206,"probRight":0.9562043795620438,"isCategorical":"False","feature":51,"split":0,"leftChild":{"id":30,"numSamples":12,"probLeft":0.25,"probRight":0.75,"isCategorical":"False","feature":55,"split":9,"leftChild":{"id":31,"numSamples":3,"probLeft":0.3333333333333333,"probRight":0.6666666666666666,"isCategorical":"False","feature":49,"split":0,"leftChild":{"id":32,"numSamples":1,"prediction":[0.0,0.0625]},"rightChild": {"id":33,"numSamples":2,"prediction":[0.0625,0.0]}},"rightChild": {"id":34,"numSamples":9,"prediction":[0.0,0.0625]}},"rightChild": {"id":35,"numSamples":262,"probLeft":0.9961832061068703,"probRight":0.003816793893129771,"isCategorical":"False","feature":42,"split":0,"leftChild":{"id":36,"numSamples":261,"probLeft":0.09961685823754789,"probRight":0.9003831417624522,"isCategorical":"False","feature":22,"split":0,"leftChild":{"id":37,"numSamples":26,"prediction":[0.004807692307692308,0.057692307692307696]},"rightChild": {"id":38,"numSamples":235,"prediction":[0.0,0.0625]}},"rightChild": {"id":39,"numSamples":1,"prediction":[0.0625,0.0]}}},"rightChild": {"id":40,"numSamples":34,"probLeft":0.5294117647058824,"probRight":0.47058823529411764,"isCategorical":"False","feature":18,"split":0,"leftChild":{"id":41,"numSamples":18,"probLeft":0.7777777777777778,"probRight":0.2222222222222222,"isCategorical":"False","feature":42,"split":0,"leftChild":{"id":42,"numSamples":14,"probLeft":0.9285714285714286,"probRight":0.07142857142857142,"isCategorical":"False","feature":52,"split":0,"leftChild":{"id":43,"numSamples":13,"prediction":[0.0625,0.0]},"rightChild": {"id":44,"numSamples":1,"prediction":[0.0,0.0625]}},"rightChild": {"id":45,"numSamples":4,"probLeft":0.5,"probRight":0.5,"isCategorical":"False","feature":15,"split":0,"leftChild":{"id":46,"numSamples":2,"prediction":[0.0625,0.0]},"rightChild": {"id":47,"numSamples":2,"prediction":[0.0,0.0625]}}},"rightChild": {"id":48,"numSamples":16,"probLeft":0.5,"probRight":0.5,"isCategorical":"False","feature":2,"split":0,"leftChild":{"id":49,"numSamples":8,"probLeft":0.75,"probRight":0.25,"isCategorical":"False","feature":18,"split":2,"leftChild":{"id":50,"numSamples":6,"prediction":[0.041666666666666664,0.020833333333333332]},"rightChild": {"id":51,"numSamples":2,"prediction":[0.0,0.0625]}},"rightChild": {"id":52,"numSamples":8,"probLeft":0.875,"probRight":0.125,"isCategorical":"False","feature":18,"split":2,"leftChild":{"id":53,"numSamples":7,"prediction":[0.0,0.0625]},"rightChild": {"id":54,"numSamples":1,"prediction":[0.0625,0.0]}}}}}},{"id":0,"numSamples":2319,"probLeft":0.8223372143165157,"probRight":0.17766278568348426,"isCategorical":"False","feature":6,"split":0,"leftChild":{"id":1,"numSamples":1907,"probLeft":0.649187205034085,"probRight":0.35081279496591505,"isCategorical":"False","feature":51,"split":0,"leftChild":{"id":2,"numSamples":1238,"probLeft":0.6470113085621971,"probRight":0.3529886914378029,"isCategorical":"False","feature":24,"split":0,"leftChild":{"id":3,"numSamples":801,"probLeft":0.7453183520599251,"probRight":0.2546816479400749,"isCategorical":"False","feature":20,"split":0,"leftChild":{"id":4,"numSamples":597,"probLeft":0.7353433835845896,"probRight":0.2646566164154104,"isCategorical":"False","feature":26,"split":0,"leftChild":{"id":5,"numSamples":439,"prediction":[0.054154829545454544,0.008345170454545454]},"rightChild": {"id":6,"numSamples":158,"prediction":[0.0625,0.0]}},"rightChild": {"id":7,"numSamples":204,"probLeft":0.3235294117647059,"probRight":0.6764705882352942,"isCategorical":"False","feature":55,"split":5,"leftChild":{"id":8,"numSamples":66,"prediction":[0.05592105263157895,0.006578947368421052]},"rightChild": {"id":9,"numSamples":138,"prediction":[0.03592289719626168,0.026577102803738317]}}},"rightChild": {"id":10,"numSamples":437,"probLeft":0.6338672768878718,"probRight":0.36613272311212813,"isCategorical":"False","feature":34,"split":0,"leftChild":{"id":11,"numSamples":277,"probLeft":0.9963898916967509,"probRight":0.0036101083032490976,"isCategorical":"False","feature":13,"split":2,"leftChild":{"id":12,"numSamples":276,"prediction":[0.06182359307359307,0.0006764069264069264]},"rightChild": {"id":13,"numSamples":1,"prediction":[0.0,0.0625]}},"rightChild": {"id":14,"numSamples":160,"prediction":[0.0625,0.0]}}},"rightChild": {"id":15,"numSamples":669,"probLeft":0.8893871449925261,"probRight":0.11061285500747384,"isCategorical":"False","feature":36,"split":0,"leftChild":{"id":16,"numSamples":595,"probLeft":0.9226890756302522,"probRight":0.0773109243697479,"isCategorical":"False","feature":24,"split":0,"leftChild":{"id":17,"numSamples":549,"probLeft":0.40255009107468126,"probRight":0.5974499089253188,"isCategorical":"False","feature":54,"split":2,"leftChild":{"id":18,"numSamples":221,"prediction":[0.03884180790960452,0.02365819209039548]},"rightChild": {"id":19,"numSamples":328,"prediction":[0.005934343434343434,0.05656565656565657]}},"rightChild": {"id":20,"numSamples":46,"probLeft":0.9130434782608695,"probRight":0.08695652173913043,"isCategorical":"False","feature":20,"split":1,"leftChild":{"id":21,"numSamples":42,"prediction":[0.059322033898305086,0.0031779661016949155]},"rightChild": {"id":22,"numSamples":4,"prediction":[0.044642857142857144,0.017857142857142856]}}},"rightChild": {"id":23,"numSamples":74,"probLeft":0.8648648648648649,"probRight":0.13513513513513514,"isCategorical":"False","feature":52,"split":0,"leftChild":{"id":24,"numSamples":64,"probLeft":0.890625,"probRight":0.109375,"isCategorical":"False","feature":54,"split":4,"leftChild":{"id":25,"numSamples":57,"prediction":[0.061155913978494625,0.0013440860215053765]},"rightChild": {"id":26,"numSamples":7,"prediction":[0.0234375,0.0390625]}},"rightChild": {"id":27,"numSamples":10,"probLeft":0.8,"probRight":0.2,"isCategorical":"False","feature":26,"split":0,"leftChild":{"id":28,"numSamples":8,"prediction":[0.017857142857142856,0.044642857142857144]},"rightChild": {"id":29,"numSamples":2,"prediction":[0.0625,0.0]}}}}},"rightChild": {"id":30,"numSamples":412,"probLeft":0.9951456310679612,"probRight":0.0048543689320388345,"isCategorical":"False","feature":32,"split":1,"leftChild":{"id":31,"numSamples":410,"probLeft":0.9829268292682927,"probRight":0.01707317073170732,"isCategorical":"False","feature":25,"split":0,"leftChild":{"id":32,"numSamples":403,"probLeft":0.9975186104218362,"probRight":0.0024813895781637717,"isCategorical":"False","feature":40,"split":0,"leftChild":{"id":33,"numSamples":402,"probLeft":0.9900497512437811,"probRight":0.009950248756218905,"isCategorical":"False","feature":41,"split":0,"leftChild":{"id":34,"numSamples":398,"prediction":[0.0021272285251215557,0.06037277147487844]},"rightChild": {"id":35,"numSamples":4,"prediction":[0.020833333333333332,0.041666666666666664]}},"rightChild": {"id":36,"numSamples":1,"prediction":[0.0625,0.0]}},"rightChild": {"id":37,"numSamples":7,"probLeft":0.7142857142857143,"probRight":0.2857142857142857,"isCategorical":"False","feature":5,"split":0,"leftChild":{"id":38,"numSamples":5,"probLeft":0.8,"probRight":0.2,"isCategorical":"False","feature":25,"split":2,"leftChild":{"id":39,"numSamples":4,"prediction":[0.0,0.0625]},"rightChild": {"id":40,"numSamples":1,"prediction":[0.0625,0.0]}},"rightChild": {"id":41,"numSamples":2,"prediction":[0.0625,0.0]}}},"rightChild": {"id":42,"numSamples":2,"prediction":[0.0625,0.0]}}},{"id":0,"numSamples":2326,"probLeft":0.5743766122098022,"probRight":0.42562338779019776,"isCategorical":"False","feature":51,"split":0,"leftChild":{"id":1,"numSamples":1336,"probLeft":0.9214071856287425,"probRight":0.07859281437125748,"isCategorical":"False","feature":10,"split":0,"leftChild":{"id":2,"numSamples":1231,"probLeft":0.735174654752234,"probRight":0.264825345247766,"isCategorical":"False","feature":25,"split":0,"leftChild":{"id":3,"numSamples":905,"probLeft":0.958011049723757,"probRight":0.041988950276243095,"isCategorical":"False","feature":5,"split":0,"leftChild":{"id":4,"numSamples":867,"probLeft":0.6851211072664359,"probRight":0.314878892733564,"isCategorical":"False","feature":54,"split":2,"leftChild":{"id":5,"numSamples":594,"prediction":[0.058542576419213975,0.003957423580786026]},"rightChild": {"id":6,"numSamples":273,"prediction":[0.040625,0.021875]}},"rightChild": {"id":7,"numSamples":38,"probLeft":0.3157894736842105,"probRight":0.6842105263157895,"isCategorical":"False","feature":56,"split":84,"leftChild":{"id":8,"numSamples":12,"prediction":[0.051470588235294115,0.011029411764705883]},"rightChild": {"id":9,"numSamples":26,"prediction":[0.003289473684210526,0.05921052631578947]}}},"rightChild": {"id":10,"numSamples":326,"probLeft":0.9938650306748467,"probRight":0.006134969325153374,"isCategorical":"False","feature":18,"split":4,"leftChild":{"id":11,"numSamples":324,"probLeft":0.9845679012345679,"probRight":0.015432098765432098,"isCategorical":"False","feature":12,"split":0,"leftChild":{"id":12,"numSamples":319,"prediction":[0.06201923076923077,0.0004807692307692308]},"rightChild": {"id":13,"numSamples":5,"prediction":[0.0546875,0.0078125]}},"rightChild": {"id":14,"numSamples":2,"probLeft":0.5,"probRight":0.5,"isCategorical":"False","feature":54,"split":4,"leftChild":{"id":15,"numSamples":1,"prediction":[0.0625,0.0]},"rightChild": {"id":16,"numSamples":1,"prediction":[0.0,0.0625]}}}},"rightChild": {"id":17,"numSamples":105,"probLeft":0.7714285714285715,"probRight":0.22857142857142856,"isCategorical":"False","feature":12,"split":0,"leftChild":{"id":18,"numSamples":81,"probLeft":0.8641975308641975,"probRight":0.13580246913580246,"isCategorical":"False","feature":6,"split":0,"leftChild":{"id":19,"numSamples":70,"probLeft":0.8571428571428571,"probRight":0.14285714285714285,"isCategorical":"False","feature":34,"split":0,"leftChild":{"id":20,"numSamples":60,"prediction":[0.04146039603960396,0.02103960396039604]},"rightChild": {"id":21,"numSamples":10,"prediction":[0.0625,0.0]}},"rightChild": {"id":22,"numSamples":11,"probLeft":0.45454545454545453,"probRight":0.5454545454545454,"isCategorical":"False","feature":6,"split":0,"leftChild":{"id":23,"numSamples":5,"prediction":[0.017857142857142856,0.044642857142857144]},"rightChild": {"id":24,"numSamples":6,"prediction":[0.0,0.0625]}}},"rightChild": {"id":25,"numSamples":24,"probLeft":0.375,"probRight":0.625,"isCategorical":"False","feature":22,"split":0,"leftChild":{"id":26,"numSamples":9,"probLeft":0.5555555555555556,"probRight":0.4444444444444444,"isCategorical":"False","feature":6,"split":0,"leftChild":{"id":27,"numSamples":5,"prediction":[0.05,0.0125]},"rightChild": {"id":28,"numSamples":4,"prediction":[0.0,0.0625]}},"rightChild": {"id":29,"numSamples":15,"prediction":[0.0,0.0625]}}}},"rightChild": {"id":30,"numSamples":990,"probLeft":0.5292929292929293,"probRight":0.4707070707070707,"isCategorical":"False","feature":15,"split":0,"leftChild":{"id":31,"numSamples":524,"probLeft":0.5725190839694656,"probRight":0.42748091603053434,"isCategorical":"False","feature":54,"split":2,"leftChild":{"id":32,"numSamples":300,"probLeft":0.8766666666666667,"probRight":0.12333333333333334,"isCategorical":"False","feature":7,"split":0,"leftChild":{"id":33,"numSamples":263,"probLeft":0.7604562737642585,"probRight":0.23954372623574144,"isCategorical":"False","feature":11,"split":0,"leftChild":{"id":34,"numSamples":200,"prediction":[0.043512658227848104,0.0189873417721519]},"rightChild": {"id":35,"numSamples":63,"prediction":[0.05837912087912088,0.004120879120879121]}},"rightChild": {"id":36,"numSamples":37,"probLeft":0.32432432432432434,"probRight":0.6756756756756757,"isCategorical":"False","feature":51,"split":0,"leftChild":{"id":37,"numSamples":12,"prediction":[0.02717391304347826,0.035326086956521736]},"rightChild": {"id":38,"numSamples":25,"prediction":[0.0,0.0625]}}},"rightChild": {"id":39,"numSamples":224,"probLeft":0.9776785714285714,"probRight":0.022321428571428572,"isCategorical":"False","feature":29,"split":0,"leftChild":{"id":40,"numSamples":219,"probLeft":0.9954337899543378,"probRight":0.0045662100456621,"isCategorical":"False","feature":43,"split":0,"leftChild":{"id":41,"numSamples":218,"prediction":[0.004518072289156626,0.05798192771084337]},"rightChild": {"id":42,"numSamples":1,"prediction":[0.0625,0.0]}},"rightChild": {"id":43,"numSamples":5,"prediction":[0.0625,0.0]}}},"rightChild": {"id":44,"numSamples":466,"probLeft":0.9785407725321889,"probRight":0.02145922746781116,"isCategorical":"False","feature":45,"split":0,"leftChild":{"id":45,"numSamples":456,"probLeft":0.10307017543859649,"probRight":0.8969298245614035,"isCategorical":"False","feature":54,"split":1,"leftChild":{"id":46,"numSamples":47,"probLeft":0.9787234042553191,"probRight":0.02127659574468085,"isCategorical":"False","feature":9,"split":1,"leftChild":{"id":47,"numSamples":46,"prediction":[0.015398550724637682,0.04710144927536232]},"rightChild": {"id":48,"numSamples":1,"prediction":[0.0625,0.0]}},"rightChild": {"id":49,"numSamples":409,"probLeft":0.9951100244498777,"probRight":0.004889975550122249,"isCategorical":"False","feature":42,"split":0,"leftChild":{"id":50,"numSamples":407,"prediction":[0.0024262422360248445,0.06007375776397515]},"rightChild": {"id":51,"numSamples":2,"prediction":[0.05,0.0125]}}},"rightChild": {"id":52,"numSamples":10,"probLeft":0.9,"probRight":0.1,"isCategorical":"False","feature":25,"split":0,"leftChild":{"id":53,"numSamples":9,"probLeft":0.7777777777777778,"probRight":0.2222222222222222,"isCategorical":"False","feature":32,"split":0,"leftChild":{"id":54,"numSamples":7,"prediction":[0.0625,0.0]},"rightChild": {"id":55,"numSamples":2,"prediction":[0.0,0.0625]}},"rightChild": {"id":56,"numSamples":1,"prediction":[0.0,0.0625]}}}}},{"id":0,"numSamples":2331,"probLeft":0.5697125697125697,"probRight":0.4302874302874303,"isCategorical":"False","feature":55,"split":18,"leftChild":{"id":1,"numSamples":1328,"probLeft":0.7673192771084337,"probRight":0.23268072289156627,"isCategorical":"False","feature":20,"split":0,"leftChild":{"id":2,"numSamples":1019,"probLeft":0.9391560353287537,"probRight":0.06084396467124632,"isCategorical":"False","feature":52,"split":0,"leftChild":{"id":3,"numSamples":957,"probLeft":0.8589341692789969,"probRight":0.14106583072100312,"isCategorical":"False","feature":35,"split":0,"leftChild":{"id":4,"numSamples":822,"probLeft":0.98661800486618,"probRight":0.01338199513381995,"isCategorical":"False","feature":23,"split":0,"leftChild":{"id":5,"numSamples":811,"prediction":[0.05684944968553459,0.005650550314465408]},"rightChild": {"id":6,"numSamples":11,"prediction":[0.014705882352941176,0.04779411764705882]}},"rightChild": {"id":7,"numSamples":135,"probLeft":0.9777777777777777,"probRight":0.022222222222222223,"isCategorical":"False","feature":7,"split":0,"leftChild":{"id":8,"numSamples":132,"prediction":[0.062209302325581396,0.00029069767441860465]},"rightChild": {"id":9,"numSamples":3,"prediction":[0.05357142857142857,0.008928571428571428]}}},"rightChild": {"id":10,"numSamples":62,"probLeft":0.7096774193548387,"probRight":0.2903225806451613,"isCategorical":"False","feature":15,"split":0,"leftChild":{"id":11,"numSamples":44,"probLeft":0.6818181818181818,"probRight":0.3181818181818182,"isCategorical":"False","feature":24,"split":0,"leftChild":{"id":12,"numSamples":30,"prediction":[0.017857142857142856,0.044642857142857144]},"rightChild": {"id":13,"numSamples":14,"prediction":[0.0625,0.0]}},"rightChild": {"id":14,"numSamples":18,"probLeft":0.9444444444444444,"probRight":0.05555555555555555,"isCategorical":"False","feature":10,"split":1,"leftChild":{"id":15,"numSamples":17,"prediction":[0.0,0.0625]},"rightChild": {"id":16,"numSamples":1,"prediction":[0.0625,0.0]}}}},"rightChild": {"id":17,"numSamples":309,"probLeft":0.8284789644012945,"probRight":0.1715210355987055,"isCategorical":"False","feature":24,"split":0,"leftChild":{"id":18,"numSamples":256,"probLeft":0.7265625,"probRight":0.2734375,"isCategorical":"False","feature":6,"split":0,"leftChild":{"id":19,"numSamples":186,"probLeft":0.5161290322580645,"probRight":0.4838709677419355,"isCategorical":"False","feature":51,"split":0,"leftChild":{"id":20,"numSamples":96,"prediction":[0.05082831325301205,0.011671686746987951]},"rightChild": {"id":21,"numSamples":90,"prediction":[0.023674242424242424,0.038825757575757576]}},"rightChild": {"id":22,"numSamples":70,"probLeft":0.9857142857142858,"probRight":0.014285714285714285,"isCategorical":"False","feature":45,"split":0,"leftChild":{"id":23,"numSamples":69,"prediction":[0.0,0.0625]},"rightChild": {"id":24,"numSamples":1,"prediction":[0.0625,0.0]}}},"rightChild": {"id":25,"numSamples":53,"prediction":[0.0625,0.0]}}},"rightChild": {"id":26,"numSamples":1003,"probLeft":0.3728813559322034,"probRight":0.6271186440677966,"isCategorical":"False","feature":51,"split":0,"leftChild":{"id":27,"numSamples":374,"probLeft":0.7566844919786097,"probRight":0.24331550802139038,"isCategorical":"False","feature":54,"split":4,"leftChild":{"id":28,"numSamples":283,"probLeft":0.43109540636042404,"probRight":0.568904593639576,"isCategorical":"False","feature":56,"split":224,"leftChild":{"id":29,"numSamples":122,"probLeft":0.9344262295081968,"probRight":0.06557377049180328,"isCategorical":"False","feature":20,"split":2,"leftChild":{"id":30,"numSamples":114,"prediction":[0.04781626506024096,0.014683734939759037]},"rightChild": {"id":31,"numSamples":8,"prediction":[0.004807692307692308,0.057692307692307696]}},"rightChild": {"id":32,"numSamples":161,"probLeft":0.2546583850931677,"probRight":0.7453416149068323,"isCategorical":"False","feature":24,"split":0,"leftChild":{"id":33,"numSamples":41,"prediction":[0.04662698412698413,0.015873015873015872]},"rightChild": {"id":34,"numSamples":120,"prediction":[0.06149193548387097,0.0010080645161290322]}}},"rightChild": {"id":35,"numSamples":91,"probLeft":0.6813186813186813,"probRight":0.31868131868131866,"isCategorical":"False","feature":52,"split":0,"leftChild":{"id":36,"numSamples":62,"probLeft":0.6774193548387096,"probRight":0.3225806451612903,"isCategorical":"False","feature":4,"split":0,"leftChild":{"id":37,"numSamples":42,"prediction":[0.04800724637681159,0.014492753623188406]},"rightChild": {"id":38,"numSamples":20,"prediction":[0.017045454545454544,0.045454545454545456]}},"rightChild": {"id":39,"numSamples":29,"probLeft":0.41379310344827586,"probRight":0.5862068965517241,"isCategorical":"False","feature":2,"split":0,"leftChild":{"id":40,"numSamples":12,"prediction":[0.020833333333333332,0.041666666666666664]},"rightChild": {"id":41,"numSamples":17,"prediction":[0.0,0.0625]}}}},"rightChild": {"id":42,"numSamples":629,"probLeft":0.22416534181240064,"probRight":0.7758346581875993,"isCategorical":"False","feature":51,"split":0,"leftChild":{"id":43,"numSamples":141,"probLeft":0.9432624113475178,"probRight":0.05673758865248227,"isCategorical":"False","feature":48,"split":0,"leftChild":{"id":44,"numSamples":133,"probLeft":0.9097744360902256,"probRight":0.09022556390977443,"isCategorical":"False","feature":34,"split":0,"leftChild":{"id":45,"numSamples":121,"prediction":[0.013888888888888888,0.04861111111111111]},"rightChild": {"id":46,"numSamples":12,"prediction":[0.05514705882352941,0.007352941176470588]}},"rightChild": {"id":47,"numSamples":8,"prediction":[0.0625,0.0]}},"rightChild": {"id":48,"numSamples":488,"probLeft":0.9897540983606558,"probRight":0.010245901639344262,"isCategorical":"False","feature":31,"split":0,"leftChild":{"id":49,"numSamples":483,"probLeft":0.989648033126294,"probRight":0.010351966873706004,"isCategorical":"False","feature":38,"split":0,"leftChild":{"id":50,"numSamples":478,"prediction":[0.0024231283422459894,0.06007687165775401]},"rightChild": {"id":51,"numSamples":5,"prediction":[0.04861111111111111,0.013888888888888888]}},"rightChild": {"id":52,"numSamples":5,"prediction":[0.0625,0.0]}}}}},{"id":0,"numSamples":2303,"probLeft":0.8671298306556665,"probRight":0.1328701693443335,"isCategorical":"False","feature":22,"split":0,"leftChild":{"id":1,"numSamples":1997,"probLeft":0.9058587881822734,"probRight":0.09414121181772658,"isCategorical":"False","feature":23,"split":0,"leftChild":{"id":2,"numSamples":1809,"probLeft":0.9060254284134881,"probRight":0.09397457158651189,"isCategorical":"False","feature":6,"split":0,"leftChild":{"id":3,"numSamples":1639,"probLeft":0.8749237339841367,"probRight":0.12507626601586333,"isCategorical":"False","feature":51,"split":0,"leftChild":{"id":4,"numSamples":1434,"probLeft":0.7329149232914923,"probRight":0.2670850767085077,"isCategorical":"False","feature":25,"split":0,"leftChild":{"id":5,"numSamples":1051,"prediction":[0.053778206650831356,0.008721793349168646]},"rightChild": {"id":6,"numSamples":383,"prediction":[0.06209481361426256,0.0004051863857374392]}},"rightChild": {"id":7,"numSamples":205,"probLeft":0.8341463414634146,"probRight":0.16585365853658537,"isCategorical":"False","feature":8,"split":0,"leftChild":{"id":8,"numSamples":171,"prediction":[0.02557915057915058,0.03692084942084942]},"rightChild": {"id":9,"numSamples":34,"prediction":[0.001201923076923077,0.06129807692307692]}}},"rightChild": {"id":10,"numSamples":170,"probLeft":0.9588235294117647,"probRight":0.041176470588235294,"isCategorical":"False","feature":26,"split":0,"leftChild":{"id":11,"numSamples":163,"probLeft":0.27607361963190186,"probRight":0.7239263803680982,"isCategorical":"False","feature":54,"split":2,"leftChild":{"id":12,"numSamples":45,"prediction":[0.0125,0.05]},"rightChild": {"id":13,"numSamples":118,"prediction":[0.002377717391304348,0.060122282608695655]}},"rightChild": {"id":14,"numSamples":7,"prediction":[0.0625,0.0]}}},"rightChild": {"id":15,"numSamples":188,"probLeft":0.973404255319149,"probRight":0.026595744680851064,"isCategorical":"False","feature":29,"split":0,"leftChild":{"id":16,"numSamples":183,"probLeft":0.06557377049180328,"probRight":0.9344262295081968,"isCategorical":"False","feature":55,"split":7,"leftChild":{"id":17,"numSamples":12,"probLeft":0.16666666666666666,"probRight":0.8333333333333334,"isCategorical":"False","feature":18,"split":0,"leftChild":{"id":18,"numSamples":2,"prediction":[0.0,0.0625]},"rightChild": {"id":19,"numSamples":10,"prediction":[0.052884615384615384,0.009615384615384616]}},"rightChild": {"id":20,"numSamples":171,"probLeft":0.9766081871345029,"probRight":0.023391812865497075,"isCategorical":"False","feature":49,"split":0,"leftChild":{"id":21,"numSamples":167,"prediction":[0.002819548872180451,0.05968045112781955]},"rightChild": {"id":22,"numSamples":4,"prediction":[0.046875,0.015625]}}},"rightChild": {"id":23,"numSamples":5,"prediction":[0.0625,0.0]}}},"rightChild": {"id":24,"numSamples":306,"probLeft":0.26143790849673204,"probRight":0.738562091503268,"isCategorical":"False","feature":52,"split":0,"leftChild":{"id":25,"numSamples":80,"probLeft":0.975,"probRight":0.025,"isCategorical":"False","feature":26,"split":0,"leftChild":{"id":26,"numSamples":78,"probLeft":0.7564102564102564,"probRight":0.24358974358974358,"isCategorical":"False","feature":36,"split":0,"leftChild":{"id":27,"numSamples":59,"probLeft":0.7627118644067796,"probRight":0.23728813559322035,"isCategorical":"False","feature":51,"split":0,"leftChild":{"id":28,"numSamples":45,"prediction":[0.0017605633802816902,0.06073943661971831]},"rightChild": {"id":29,"numSamples":14,"prediction":[0.005681818181818182,0.056818181818181816]}},"rightChild": {"id":30,"numSamples":19,"probLeft":0.7894736842105263,"probRight":0.21052631578947367,"isCategorical":"False","feature":51,"split":0,"leftChild":{"id":31,"numSamples":15,"prediction":[0.052083333333333336,0.010416666666666666]},"rightChild": {"id":32,"numSamples":4,"prediction":[0.0,0.0625]}}},"rightChild": {"id":33,"numSamples":2,"prediction":[0.0625,0.0]}},"rightChild": {"id":34,"numSamples":226,"prediction":[0.0,0.0625]}}},{"id":0,"numSamples":2284,"probLeft":0.8204903677758318,"probRight":0.17950963222416813,"isCategorical":"False","feature":6,"split":0,"leftChild":{"id":1,"numSamples":1874,"probLeft":0.8340448239060833,"probRight":0.16595517609391675,"isCategorical":"False","feature":52,"split":0,"leftChild":{"id":2,"numSamples":1563,"probLeft":0.8490083173384517,"probRight":0.1509916826615483,"isCategorical":"False","feature":54,"split":3,"leftChild":{"id":3,"numSamples":1327,"probLeft":0.9125847776940467,"probRight":0.08741522230595328,"isCategorical":"False","feature":15,"split":0,"leftChild":{"id":4,"numSamples":1211,"probLeft":0.9843104872006606,"probRight":0.01568951279933939,"isCategorical":"False","feature":8,"split":0,"leftChild":{"id":5,"numSamples":1192,"prediction":[0.05858753315649867,0.003912466843501326]},"rightChild": {"id":6,"numSamples":19,"prediction":[0.025,0.0375]}},"rightChild": {"id":7,"numSamples":116,"probLeft":0.5172413793103449,"probRight":0.4827586206896552,"isCategorical":"False","feature":51,"split":0,"leftChild":{"id":8,"numSamples":60,"prediction":[0.04207920792079208,0.02042079207920792]},"rightChild": {"id":9,"numSamples":56,"prediction":[0.012768817204301076,0.04973118279569892]}}},"rightChild": {"id":10,"numSamples":236,"probLeft":0.9194915254237288,"probRight":0.08050847457627118,"isCategorical":"False","feature":22,"split":0,"leftChild":{"id":11,"numSamples":217,"probLeft":0.7741935483870968,"probRight":0.22580645161290322,"isCategorical":"False","feature":50,"split":0,"leftChild":{"id":12,"numSamples":168,"prediction":[0.03264925373134328,0.029850746268656716]},"rightChild": {"id":13,"numSamples":49,"prediction":[0.05592105263157895,0.006578947368421052]}},"rightChild": {"id":14,"numSamples":19,"prediction":[0.0,0.0625]}}},"rightChild": {"id":15,"numSamples":311,"probLeft":0.26366559485530544,"probRight":0.7363344051446945,"isCategorical":"False","feature":51,"split":0,"leftChild":{"id":16,"numSamples":82,"probLeft":0.7560975609756098,"probRight":0.24390243902439024,"isCategorical":"False","feature":20,"split":0,"leftChild":{"id":17,"numSamples":62,"probLeft":0.7096774193548387,"probRight":0.2903225806451613,"isCategorical":"False","feature":54,"split":3,"leftChild":{"id":18,"numSamples":44,"prediction":[0.049107142857142856,0.013392857142857142]},"rightChild": {"id":19,"numSamples":18,"prediction":[0.020833333333333332,0.041666666666666664]}},"rightChild": {"id":20,"numSamples":20,"probLeft":0.95,"probRight":0.05,"isCategorical":"False","feature":45,"split":0,"leftChild":{"id":21,"numSamples":19,"prediction":[0.006048387096774193,0.056451612903225805]},"rightChild": {"id":22,"numSamples":1,"prediction":[0.0625,0.0]}}},"rightChild": {"id":23,"numSamples":229,"probLeft":0.9868995633187773,"probRight":0.013100436681222707,"isCategorical":"False","feature":45,"split":0,"leftChild":{"id":24,"numSamples":226,"probLeft":0.9823008849557522,"probRight":0.017699115044247787,"isCategorical":"False","feature":24,"split":0,"leftChild":{"id":25,"numSamples":222,"prediction":[0.0024441340782122905,0.06005586592178771]},"rightChild": {"id":26,"numSamples":4,"prediction":[0.0625,0.0]}},"rightChild": {"id":27,"numSamples":3,"prediction":[0.0625,0.0]}}}},"rightChild": {"id":28,"numSamples":410,"probLeft":0.5048780487804878,"probRight":0.4951219512195122,"isCategorical":"False","feature":52,"split":0,"leftChild":{"id":29,"numSamples":207,"probLeft":0.9758454106280193,"probRight":0.024154589371980676,"isCategorical":"False","feature":45,"split":0,"leftChild":{"id":30,"numSamples":202,"probLeft":0.2079207920792079,"probRight":0.7920792079207921,"isCategorical":"False","feature":51,"split":0,"leftChild":{"id":31,"numSamples":42,"probLeft":0.9047619047619048,"probRight":0.09523809523809523,"isCategorical":"False","feature":20,"split":2,"leftChild":{"id":32,"numSamples":38,"prediction":[0.012711864406779662,0.04978813559322034]},"rightChild": {"id":33,"numSamples":4,"prediction":[0.0546875,0.0078125]}},"rightChild": {"id":34,"numSamples":160,"probLeft":0.98125,"probRight":0.01875,"isCategorical":"False","feature":26,"split":0,"leftChild":{"id":35,"numSamples":157,"prediction":[0.001984126984126984,0.060515873015873016]},"rightChild": {"id":36,"numSamples":3,"prediction":[0.0625,0.0]}}},"rightChild": {"id":37,"numSamples":5,"probLeft":0.8,"probRight":0.2,"isCategorical":"False","feature":14,"split":0,"leftChild":{"id":38,"numSamples":4,"probLeft":0.75,"probRight":0.25,"isCategorical":"False","feature":35,"split":0,"leftChild":{"id":39,"numSamples":3,"prediction":[0.0625,0.0]},"rightChild": {"id":40,"numSamples":1,"prediction":[0.0,0.0625]}},"rightChild": {"id":41,"numSamples":1,"prediction":[0.0625,0.0]}}},"rightChild": {"id":42,"numSamples":203,"probLeft":0.059113300492610835,"probRight":0.9408866995073891,"isCategorical":"False","feature":20,"split":0,"leftChild":{"id":43,"numSamples":12,"probLeft":0.4166666666666667,"probRight":0.5833333333333334,"isCategorical":"False","feature":54,"split":4,"leftChild":{"id":44,"numSamples":5,"prediction":[0.0,0.0625]},"rightChild": {"id":45,"numSamples":7,"probLeft":0.2857142857142857,"probRight":0.7142857142857143,"isCategorical":"False","feature":2,"split":0,"leftChild":{"id":46,"numSamples":2,"prediction":[0.025,0.0375]},"rightChild": {"id":47,"numSamples":5,"prediction":[0.0,0.0625]}}},"rightChild": {"id":48,"numSamples":191,"probLeft":0.9947643979057592,"probRight":0.005235602094240838,"isCategorical":"False","feature":45,"split":0,"leftChild":{"id":49,"numSamples":190,"prediction":[0.0,0.0625]},"rightChild": {"id":50,"numSamples":1,"prediction":[0.0625,0.0]}}}}},{"id":0,"numSamples":2297,"probLeft":0.522855898998694,"probRight":0.47714410100130605,"isCategorical":"False","feature":20,"split":0,"leftChild":{"id":1,"numSamples":1201,"probLeft":0.8825978351373855,"probRight":0.11740216486261448,"isCategorical":"False","feature":11,"split":1,"leftChild":{"id":2,"numSamples":1060,"probLeft":0.7490566037735849,"probRight":0.2509433962264151,"isCategorical":"False","feature":26,"split":0,"leftChild":{"id":3,"numSamples":794,"probLeft":0.7367758186397985,"probRight":0.26322418136020154,"isCategorical":"False","feature":51,"split":0,"leftChild":{"id":4,"numSamples":585,"probLeft":0.8512820512820513,"probRight":0.14871794871794872,"isCategorical":"False","feature":54,"split":3,"leftChild":{"id":5,"numSamples":498,"prediction":[0.057777078085642315,0.004722921914357683]},"rightChild": {"id":6,"numSamples":87,"prediction":[0.0388986013986014,0.0236013986013986]}},"rightChild": {"id":7,"numSamples":209,"probLeft":0.3684210526315789,"probRight":0.631578947368421,"isCategorical":"False","feature":55,"split":10,"leftChild":{"id":8,"numSamples":77,"prediction":[0.047619047619047616,0.01488095238095238]},"rightChild": {"id":9,"numSamples":132,"prediction":[0.0196256038647343,0.042874396135265704]}}},"rightChild": {"id":10,"numSamples":266,"prediction":[0.0625,0.0]}},"rightChild": {"id":11,"numSamples":141,"probLeft":0.9929078014184397,"probRight":0.0070921985815602835,"isCategorical":"False","feature":6,"split":0,"leftChild":{"id":12,"numSamples":140,"probLeft":0.9571428571428572,"probRight":0.04285714285714286,"isCategorical":"False","feature":45,"split":1,"leftChild":{"id":13,"numSamples":134,"probLeft":0.7835820895522388,"probRight":0.21641791044776118,"isCategorical":"False","feature":41,"split":0,"leftChild":{"id":14,"numSamples":105,"prediction":[0.061746987951807226,0.0007530120481927711]},"rightChild": {"id":15,"numSamples":29,"prediction":[0.0625,0.0]}},"rightChild": {"id":16,"numSamples":6,"probLeft":0.16666666666666666,"probRight":0.8333333333333334,"isCategorical":"False","feature":45,"split":1,"leftChild":{"id":17,"numSamples":1,"prediction":[0.0,0.0625]},"rightChild": {"id":18,"numSamples":5,"prediction":[0.0625,0.0]}}},"rightChild": {"id":19,"numSamples":1,"prediction":[0.0,0.0625]}}},"rightChild": {"id":20,"numSamples":1096,"probLeft":0.4416058394160584,"probRight":0.5583941605839416,"isCategorical":"False","feature":4,"split":0,"leftChild":{"id":21,"numSamples":484,"probLeft":0.7210743801652892,"probRight":0.27892561983471076,"isCategorical":"False","feature":52,"split":0,"leftChild":{"id":22,"numSamples":349,"probLeft":0.7650429799426934,"probRight":0.2349570200573066,"isCategorical":"False","feature":51,"split":0,"leftChild":{"id":23,"numSamples":267,"probLeft":0.9925093632958801,"probRight":0.00749063670411985,"isCategorical":"False","feature":32,"split":1,"leftChild":{"id":24,"numSamples":265,"prediction":[0.056295399515738496,0.006204600484261501]},"rightChild": {"id":25,"numSamples":2,"prediction":[0.0078125,0.0546875]}},"rightChild": {"id":26,"numSamples":82,"probLeft":0.7804878048780488,"probRight":0.21951219512195122,"isCategorical":"False","feature":6,"split":0,"leftChild":{"id":27,"numSamples":64,"prediction":[0.025252525252525252,0.037247474747474744]},"rightChild": {"id":28,"numSamples":18,"prediction":[0.0,0.0625]}}},"rightChild": {"id":29,"numSamples":135,"probLeft":0.1259259259259259,"probRight":0.8740740740740741,"isCategorical":"False","feature":20,"split":0,"leftChild":{"id":30,"numSamples":17,"probLeft":0.7058823529411765,"probRight":0.29411764705882354,"isCategorical":"False","feature":18,"split":3,"leftChild":{"id":31,"numSamples":12,"prediction":[0.036931818181818184,0.02556818181818182]},"rightChild": {"id":32,"numSamples":5,"prediction":[0.0,0.0625]}},"rightChild": {"id":33,"numSamples":118,"probLeft":0.9661016949152542,"probRight":0.03389830508474576,"isCategorical":"False","feature":24,"split":0,"leftChild":{"id":34,"numSamples":114,"prediction":[0.0006720430107526882,0.06182795698924731]},"rightChild": {"id":35,"numSamples":4,"prediction":[0.0625,0.0]}}}},"rightChild": {"id":36,"numSamples":612,"probLeft":0.9150326797385621,"probRight":0.08496732026143791,"isCategorical":"False","feature":36,"split":0,"leftChild":{"id":37,"numSamples":560,"probLeft":0.9767857142857143,"probRight":0.023214285714285715,"isCategorical":"False","feature":26,"split":0,"leftChild":{"id":38,"numSamples":547,"probLeft":0.979890310786106,"probRight":0.02010968921389397,"isCategorical":"False","feature":24,"split":1,"leftChild":{"id":39,"numSamples":536,"prediction":[0.003205128205128205,0.05929487179487179]},"rightChild": {"id":40,"numSamples":11,"prediction":[0.0625,0.0]}},"rightChild": {"id":41,"numSamples":13,"probLeft":0.9230769230769231,"probRight":0.07692307692307693,"isCategorical":"False","feature":22,"split":0,"leftChild":{"id":42,"numSamples":12,"prediction":[0.0625,0.0]},"rightChild": {"id":43,"numSamples":1,"prediction":[0.0,0.0625]}}},"rightChild": {"id":44,"numSamples":52,"probLeft":0.34615384615384615,"probRight":0.6538461538461539,"isCategorical":"False","feature":24,"split":0,"leftChild":{"id":45,"numSamples":18,"probLeft":0.8888888888888888,"probRight":0.1111111111111111,"isCategorical":"False","feature":45,"split":0,"leftChild":{"id":46,"numSamples":16,"prediction":[0.011160714285714286,0.05133928571428571]},"rightChild": {"id":47,"numSamples":2,"prediction":[0.0625,0.0]}},"rightChild": {"id":48,"numSamples":34,"probLeft":0.9705882352941176,"probRight":0.029411764705882353,"isCategorical":"False","feature":52,"split":0,"leftChild":{"id":49,"numSamples":33,"prediction":[0.06132075471698113,0.0011792452830188679]},"rightChild": {"id":50,"numSamples":1,"prediction":[0.0,0.0625]}}}}}},{"id":0,"numSamples":2308,"probLeft":0.824523396880416,"probRight":0.17547660311958405,"isCategorical":"False","feature":6,"split":0,"leftChild":{"id":1,"numSamples":1903,"probLeft":0.7719390436153442,"probRight":0.22806095638465582,"isCategorical":"False","feature":54,"split":3,"leftChild":{"id":2,"numSamples":1469,"probLeft":0.943498978897209,"probRight":0.05650102110279102,"isCategorical":"False","feature":23,"split":0,"leftChild":{"id":3,"numSamples":1386,"probLeft":0.9776334776334776,"probRight":0.022366522366522368,"isCategorical":"False","feature":22,"split":0,"leftChild":{"id":4,"numSamples":1355,"probLeft":0.752029520295203,"probRight":0.24797047970479705,"isCategorical":"False","feature":20,"split":0,"leftChild":{"id":5,"numSamples":1019,"prediction":[0.05824829931972789,0.004251700680272109]},"rightChild": {"id":6,"numSamples":336,"prediction":[0.046992481203007516,0.01550751879699248]}},"rightChild": {"id":7,"numSamples":31,"probLeft":0.06451612903225806,"probRight":0.9354838709677419,"isCategorical":"False","feature":55,"split":6,"leftChild":{"id":8,"numSamples":2,"prediction":[0.03125,0.03125]},"rightChild": {"id":9,"numSamples":29,"prediction":[0.0,0.0625]}}},"rightChild": {"id":10,"numSamples":83,"probLeft":0.5662650602409639,"probRight":0.43373493975903615,"isCategorical":"False","feature":7,"split":0,"leftChild":{"id":11,"numSamples":47,"probLeft":0.9361702127659575,"probRight":0.06382978723404255,"isCategorical":"False","feature":24,"split":0,"leftChild":{"id":12,"numSamples":44,"prediction":[0.021484375,0.041015625]},"rightChild": {"id":13,"numSamples":3,"prediction":[0.0625,0.0]}},"rightChild": {"id":14,"numSamples":36,"probLeft":0.2222222222222222,"probRight":0.7777777777777778,"isCategorical":"False","feature":20,"split":0,"leftChild":{"id":15,"numSamples":8,"prediction":[0.015625,0.046875]},"rightChild": {"id":16,"numSamples":28,"prediction":[0.0,0.0625]}}}},"rightChild": {"id":17,"numSamples":434,"probLeft":0.5299539170506913,"probRight":0.4700460829493088,"isCategorical":"False","feature":20,"split":0,"leftChild":{"id":18,"numSamples":230,"probLeft":0.908695652173913,"probRight":0.09130434782608696,"isCategorical":"False","feature":22,"split":0,"leftChild":{"id":19,"numSamples":209,"probLeft":0.9234449760765551,"probRight":0.07655502392344497,"isCategorical":"False","feature":15,"split":0,"leftChild":{"id":20,"numSamples":193,"prediction":[0.044070512820512824,0.01842948717948718]},"rightChild": {"id":21,"numSamples":16,"prediction":[0.0,0.0625]}},"rightChild": {"id":22,"numSamples":21,"probLeft":0.5714285714285714,"probRight":0.42857142857142855,"isCategorical":"False","feature":54,"split":5,"leftChild":{"id":23,"numSamples":12,"prediction":[0.0,0.0625]},"rightChild": {"id":24,"numSamples":9,"prediction":[0.008333333333333333,0.05416666666666667]}}},"rightChild": {"id":25,"numSamples":204,"probLeft":0.9754901960784313,"probRight":0.024509803921568627,"isCategorical":"False","feature":29,"split":0,"leftChild":{"id":26,"numSamples":199,"probLeft":0.9748743718592965,"probRight":0.02512562814070352,"isCategorical":"False","feature":39,"split":1,"leftChild":{"id":27,"numSamples":194,"prediction":[0.006746031746031746,0.05575396825396826]},"rightChild": {"id":28,"numSamples":5,"prediction":[0.0625,0.0]}},"rightChild": {"id":29,"numSamples":5,"prediction":[0.0625,0.0]}}}},"rightChild": {"id":30,"numSamples":405,"probLeft":0.9876543209876543,"probRight":0.012345679012345678,"isCategorical":"False","feature":31,"split":0,"leftChild":{"id":31,"numSamples":400,"probLeft":0.2075,"probRight":0.7925,"isCategorical":"False","feature":51,"split":0,"leftChild":{"id":32,"numSamples":83,"probLeft":0.9397590361445783,"probRight":0.060240963855421686,"isCategorical":"False","feature":26,"split":0,"leftChild":{"id":33,"numSamples":78,"probLeft":0.0641025641025641,"probRight":0.9358974358974359,"isCategorical":"False","feature":54,"split":1,"leftChild":{"id":34,"numSamples":5,"prediction":[0.034722222222222224,0.027777777777777776]},"rightChild": {"id":35,"numSamples":73,"prediction":[0.006610576923076923,0.05588942307692308]}},"rightChild": {"id":36,"numSamples":5,"prediction":[0.0625,0.0]}},"rightChild": {"id":37,"numSamples":317,"probLeft":0.9936908517350158,"probRight":0.006309148264984227,"isCategorical":"False","feature":6,"split":3,"leftChild":{"id":38,"numSamples":315,"probLeft":0.9936507936507937,"probRight":0.006349206349206349,"isCategorical":"False","feature":41,"split":0,"leftChild":{"id":39,"numSamples":313,"prediction":[0.0012303149606299212,0.06126968503937008]},"rightChild": {"id":40,"numSamples":2,"prediction":[0.03125,0.03125]}},"rightChild": {"id":41,"numSamples":2,"probLeft":0.5,"probRight":0.5,"isCategorical":"False","feature":54,"split":13,"leftChild":{"id":42,"numSamples":1,"prediction":[0.0625,0.0]},"rightChild": {"id":43,"numSamples":1,"prediction":[0.0,0.0625]}}}},"rightChild": {"id":44,"numSamples":5,"prediction":[0.0625,0.0]}}},{"id":0,"numSamples":2307,"probLeft":0.7511920242739488,"probRight":0.24880797572605115,"isCategorical":"False","feature":24,"split":0,"leftChild":{"id":1,"numSamples":1733,"probLeft":0.3866128101557992,"probRight":0.6133871898442008,"isCategorical":"False","feature":55,"split":9,"leftChild":{"id":2,"numSamples":670,"probLeft":0.9895522388059701,"probRight":0.010447761194029851,"isCategorical":"False","feature":19,"split":0,"leftChild":{"id":3,"numSamples":663,"probLeft":0.9653092006033183,"probRight":0.03469079939668175,"isCategorical":"False","feature":10,"split":0,"leftChild":{"id":4,"numSamples":640,"probLeft":0.453125,"probRight":0.546875,"isCategorical":"False","feature":56,"split":14,"leftChild":{"id":5,"numSamples":290,"prediction":[0.06018013100436681,0.002319868995633188]},"rightChild": {"id":6,"numSamples":350,"prediction":[0.053423713235294115,0.009076286764705883]}},"rightChild": {"id":7,"numSamples":23,"probLeft":0.5652173913043478,"probRight":0.43478260869565216,"isCategorical":"False","feature":1,"split":0,"leftChild":{"id":8,"numSamples":13,"prediction":[0.026785714285714284,0.03571428571428571]},"rightChild": {"id":9,"numSamples":10,"prediction":[0.0,0.0625]}}},"rightChild": {"id":10,"numSamples":7,"probLeft":0.5714285714285714,"probRight":0.42857142857142855,"isCategorical":"False","feature":2,"split":0,"leftChild":{"id":11,"numSamples":4,"probLeft":0.75,"probRight":0.25,"isCategorical":"False","feature":49,"split":0,"leftChild":{"id":12,"numSamples":3,"prediction":[0.03125,0.03125]},"rightChild": {"id":13,"numSamples":1,"prediction":[0.0,0.0625]}},"rightChild": {"id":14,"numSamples":3,"prediction":[0.0,0.0625]}}},"rightChild": {"id":15,"numSamples":1063,"probLeft":0.4891815616180621,"probRight":0.510818438381938,"isCategorical":"False","feature":52,"split":0,"leftChild":{"id":16,"numSamples":520,"probLeft":0.5288461538461539,"probRight":0.47115384615384615,"isCategorical":"False","feature":51,"split":0,"leftChild":{"id":17,"numSamples":275,"probLeft":0.9745454545454545,"probRight":0.025454545454545455,"isCategorical":"False","feature":22,"split":0,"leftChild":{"id":18,"numSamples":268,"prediction":[0.04792147806004619,0.01457852193995381]},"rightChild": {"id":19,"numSamples":7,"prediction":[0.0,0.0625]}},"rightChild": {"id":20,"numSamples":245,"probLeft":0.9836734693877551,"probRight":0.0163265306122449,"isCategorical":"False","feature":34,"split":1,"leftChild":{"id":21,"numSamples":241,"prediction":[0.015342377260981912,0.047157622739018086]},"rightChild": {"id":22,"numSamples":4,"prediction":[0.0625,0.0]}}},"rightChild": {"id":23,"numSamples":543,"probLeft":0.13627992633517497,"probRight":0.8637200736648251,"isCategorical":"False","feature":20,"split":0,"leftChild":{"id":24,"numSamples":74,"probLeft":0.9594594594594594,"probRight":0.04054054054054054,"isCategorical":"False","feature":50,"split":0,"leftChild":{"id":25,"numSamples":71,"prediction":[0.00995575221238938,0.05254424778761062]},"rightChild": {"id":26,"numSamples":3,"prediction":[0.0625,0.0]}},"rightChild": {"id":27,"numSamples":469,"probLeft":0.997867803837953,"probRight":0.0021321961620469083,"isCategorical":"False","feature":45,"split":0,"leftChild":{"id":28,"numSamples":468,"prediction":[0.0016778523489932886,0.060822147651006714]},"rightChild": {"id":29,"numSamples":1,"prediction":[0.0625,0.0]}}}}},"rightChild": {"id":30,"numSamples":574,"probLeft":0.9825783972125436,"probRight":0.017421602787456445,"isCategorical":"False","feature":2,"split":1,"leftChild":{"id":31,"numSamples":564,"probLeft":0.8776595744680851,"probRight":0.12234042553191489,"isCategorical":"False","feature":54,"split":3,"leftChild":{"id":32,"numSamples":495,"probLeft":0.9656565656565657,"probRight":0.03434343434343434,"isCategorical":"False","feature":15,"split":0,"leftChild":{"id":33,"numSamples":478,"probLeft":0.9916317991631799,"probRight":0.008368200836820083,"isCategorical":"False","feature":19,"split":0,"leftChild":{"id":34,"numSamples":474,"prediction":[0.06241403026134801,8.59697386519945e-05]},"rightChild": {"id":35,"numSamples":4,"prediction":[0.046875,0.015625]}},"rightChild": {"id":36,"numSamples":17,"probLeft":0.35294117647058826,"probRight":0.6470588235294118,"isCategorical":"False","feature":49,"split":0,"leftChild":{"id":37,"numSamples":6,"prediction":[0.03125,0.03125]},"rightChild": {"id":38,"numSamples":11,"prediction":[0.05263157894736842,0.009868421052631578]}}},"rightChild": {"id":39,"numSamples":69,"probLeft":0.9565217391304348,"probRight":0.043478260869565216,"isCategorical":"False","feature":15,"split":0,"leftChild":{"id":40,"numSamples":66,"probLeft":0.9242424242424242,"probRight":0.07575757575757576,"isCategorical":"False","feature":22,"split":0,"leftChild":{"id":41,"numSamples":61,"prediction":[0.061274509803921566,0.0012254901960784314]},"rightChild": {"id":42,"numSamples":5,"prediction":[0.022727272727272728,0.03977272727272727]}},"rightChild": {"id":43,"numSamples":3,"prediction":[0.0,0.0625]}}},"rightChild": {"id":44,"numSamples":10,"probLeft":0.5,"probRight":0.5,"isCategorical":"False","feature":54,"split":151,"leftChild":{"id":45,"numSamples":5,"prediction":[0.0625,0.0]},"rightChild": {"id":46,"numSamples":5,"prediction":[0.0,0.0625]}}}},{"id":0,"numSamples":2322,"probLeft":0.7411714039621017,"probRight":0.2588285960378984,"isCategorical":"False","feature":54,"split":3,"leftChild":{"id":1,"numSamples":1721,"probLeft":0.7216734456711215,"probRight":0.27832655432887854,"isCategorical":"False","feature":4,"split":0,"leftChild":{"id":2,"numSamples":1242,"probLeft":0.6988727858293076,"probRight":0.30112721417069244,"isCategorical":"False","feature":51,"split":0,"leftChild":{"id":3,"numSamples":868,"probLeft":0.988479262672811,"probRight":0.01152073732718894,"isCategorical":"False","feature":6,"split":0,"leftChild":{"id":4,"numSamples":858,"probLeft":0.9976689976689976,"probRight":0.002331002331002331,"isCategorical":"False","feature":3,"split":0,"leftChild":{"id":5,"numSamples":856,"prediction":[0.05940007293946025,0.003099927060539752]},"rightChild": {"id":6,"numSamples":2,"prediction":[0.0,0.0625]}},"rightChild": {"id":7,"numSamples":10,"probLeft":0.5,"probRight":0.5,"isCategorical":"False","feature":56,"split":50,"leftChild":{"id":8,"numSamples":5,"prediction":[0.008928571428571428,0.05357142857142857]},"rightChild": {"id":9,"numSamples":5,"prediction":[0.0,0.0625]}}},"rightChild": {"id":10,"numSamples":374,"probLeft":0.7272727272727273,"probRight":0.2727272727272727,"isCategorical":"False","feature":54,"split":2,"leftChild":{"id":11,"numSamples":272,"probLeft":0.9007352941176471,"probRight":0.09926470588235294,"isCategorical":"False","feature":7,"split":0,"leftChild":{"id":12,"numSamples":245,"prediction":[0.048153034300791556,0.014346965699208443]},"rightChild": {"id":13,"numSamples":27,"prediction":[0.010174418604651164,0.05232558139534884]}},"rightChild": {"id":14,"numSamples":102,"probLeft":0.9215686274509803,"probRight":0.0784313725490196,"isCategorical":"False","feature":36,"split":0,"leftChild":{"id":15,"numSamples":94,"prediction":[0.01393884892086331,0.048561151079136694]},"rightChild": {"id":16,"numSamples":8,"prediction":[0.0625,0.0]}}}},"rightChild": {"id":17,"numSamples":479,"probLeft":0.7348643006263048,"probRight":0.2651356993736952,"isCategorical":"False","feature":6,"split":0,"leftChild":{"id":18,"numSamples":352,"probLeft":0.5625,"probRight":0.4375,"isCategorical":"False","feature":18,"split":1,"leftChild":{"id":19,"numSamples":198,"probLeft":0.8737373737373737,"probRight":0.12626262626262627,"isCategorical":"False","feature":15,"split":0,"leftChild":{"id":20,"numSamples":173,"prediction":[0.05502717391304348,0.007472826086956522]},"rightChild": {"id":21,"numSamples":25,"prediction":[0.01636904761904762,0.046130952380952384]}},"rightChild": {"id":22,"numSamples":154,"probLeft":0.7077922077922078,"probRight":0.2922077922077922,"isCategorical":"False","feature":51,"split":0,"leftChild":{"id":23,"numSamples":109,"prediction":[0.034957627118644065,0.02754237288135593]},"rightChild": {"id":24,"numSamples":45,"prediction":[0.0030864197530864196,0.05941358024691358]}}},"rightChild": {"id":25,"numSamples":127,"probLeft":0.9763779527559056,"probRight":0.023622047244094488,"isCategorical":"False","feature":26,"split":0,"leftChild":{"id":26,"numSamples":124,"probLeft":0.9758064516129032,"probRight":0.024193548387096774,"isCategorical":"False","feature":35,"split":0,"leftChild":{"id":27,"numSamples":121,"prediction":[0.0024171270718232043,0.060082872928176795]},"rightChild": {"id":28,"numSamples":3,"prediction":[0.03125,0.03125]}},"rightChild": {"id":29,"numSamples":3,"prediction":[0.0625,0.0]}}}},"rightChild": {"id":30,"numSamples":601,"probLeft":0.9467554076539102,"probRight":0.05324459234608985,"isCategorical":"False","feature":34,"split":0,"leftChild":{"id":31,"numSamples":569,"probLeft":0.9736379613356766,"probRight":0.026362038664323375,"isCategorical":"False","feature":28,"split":0,"leftChild":{"id":32,"numSamples":554,"probLeft":0.6588447653429603,"probRight":0.34115523465703973,"isCategorical":"False","feature":22,"split":0,"leftChild":{"id":33,"numSamples":365,"probLeft":0.7178082191780822,"probRight":0.2821917808219178,"isCategorical":"False","feature":55,"split":108,"leftChild":{"id":34,"numSamples":262,"prediction":[0.01927860696517413,0.04322139303482587]},"rightChild": {"id":35,"numSamples":103,"prediction":[0.005933544303797469,0.056566455696202535]}},"rightChild": {"id":36,"numSamples":189,"probLeft":0.9947089947089947,"probRight":0.005291005291005291,"isCategorical":"False","feature":41,"split":0,"leftChild":{"id":37,"numSamples":188,"prediction":[0.0,0.0625]},"rightChild": {"id":38,"numSamples":1,"prediction":[0.0625,0.0]}}},"rightChild": {"id":39,"numSamples":15,"prediction":[0.0625,0.0]}},"rightChild": {"id":40,"numSamples":32,"probLeft":0.90625,"probRight":0.09375,"isCategorical":"False","feature":6,"split":0,"leftChild":{"id":41,"numSamples":29,"probLeft":0.9655172413793104,"probRight":0.034482758620689655,"isCategorical":"False","feature":12,"split":0,"leftChild":{"id":42,"numSamples":28,"probLeft":0.8571428571428571,"probRight":0.14285714285714285,"isCategorical":"False","feature":18,"split":2,"leftChild":{"id":43,"numSamples":24,"prediction":[0.0625,0.0]},"rightChild": {"id":44,"numSamples":4,"prediction":[0.05,0.0125]}},"rightChild": {"id":45,"numSamples":1,"prediction":[0.0,0.0625]}},"rightChild": {"id":46,"numSamples":3,"prediction":[0.0,0.0625]}}}}]